Workbook

Sheet Part 1 - Overview
A1: Slide No | B1: Slide Title | C1: Metric / Data Point | D1: Value | E1: Notes / Key Message
A2: Slide 1 | B2: Title Slide | C2: Report Week | D2: 36 | E2: สรุปผลการดำเนินงานโครงการติดตั้งโครงข่ายโทรคมนาคม HAE และ TME ประจำสัปดาห์ที่ 36
A3: Slide 1 | B3: Executive Bottom Line | C3: HAE M1 Avg | D3: ='Part 2 - Aging'!D3 -> 3.1306306 | E3: หน้างานยังคงเดินหน้าอย่างรวดเร็ว แต่ระบบเอกสารยังมีปัญหาคอขวด
A4: Slide 1 | B4: Executive Bottom Line | C4: TME M1 Avg | D4: ='Part 2 - Aging'!D5 -> 15.031579 | E4: ข้อมูลดิบอาจมีความคลาดเคลื่อนในระบบ
A5: Slide 2 | B5: Portfolio Performance Snapshot | C5: Overall Progress | E5: สัดส่วนของ HAE และ TME ในพอร์ตโฟลิโอทั้งหมด
A6: Slide 2 | B6: Smart QC Overview | C6: Pass Rate | E6: อัตราการผ่านการตรวจสอบคุณภาพเปรียบเทียบสองโครงการ
A7: Slide 2 | B7: Operation Error & Defect Analysis | C7: Defect Issue 1 | E7: การขาดอุปกรณ์ป้องกัน PPE / ส่งข้อมูลไม่ครบ
A8: Slide 2 | B8: Improvement Plan for On-Site Quality | C8: Action Plan | E8: บูรณาการ AIS SPE Standards อย่างเคร่งครัด

Sheet Part 2 - Aging
A1: Slide No | B1: Slide Title | C1: Category / Person | D1: M1 Aging | E1: Notes
A2: Slide 3 | B2: The Execution Paradox | C2: Overall Bottleneck | E2: หน้างานทำได้เร็ว แต่กระบวนการตรวจรับเอกสารล่าช้า
A3: Slide 4 | B3: 1st Milestone AGING Analysis (HAE-MBB) | C3: HAE M1 | D3: =AVERAGEIF('2026'!G:G,"HAE",'2026'!BD:BD) -> 3.1306306 | E3: เปรียบเทียบระยะเวลาปิด M1 (HAE-MBB) | G3: HAE-MBB
A4: Slide 4 | B4: 2nd Milestone AGING Analysis (HAE-MBB) | C4: HAE M2 | D4: =AVERAGEIF('2026'!G:G,"HAE",'2026'!BE:BE) -> 6.6576577 | E4: ความท้าทายในการปิดเอกสาร M2 ที่กินระยะเวลานาน (HAE-MBB) | G4: HAE-MBB
A5: Slide 5 | B5: 1st Milestone AGING Analysis (TME-MBB) | C5: TME M1 | D5: =AVERAGEIF('2026'!G:G,"TME",'2026'!BE:BE) -> 15.031579 | E5: เปรียบเทียบระยะเวลาปิด M1(TME-MBB) | G5: TME-MBB
A6: Slide 5 | B6: 2nd Milestone AGING Analysis (TME-IPRAN) | C6: TME M2 | D6: 17.12 | E6: ความท้าทายในการปิดเอกสาร M2 ที่กินระยะเวลานาน (TME-IPRAN) | G6: TME-IPRAN
A7: Slide 5 | B7: 2nd Milestone AGING Analysis (TME-MBB) | C7: TME M2 | D7: 3.5 | E7: ความท้าทายในการปิดเอกสาร M2 ที่กินระยะเวลานาน (TME-MBB) | G7: TME-MBB
A8: Slide 6 | B8: Performance by PE Owner: Adisak (Average M1+M2) | C8: Adisak Chanmao (Average M1+M2) | D8: =AVERAGE(D3:D4) -> 4.8941441 | E8: HAE-MBB
A9: Slide 6 | B9: Performance by PE Owner: Palagon (Average M1+M2) | C9: Palagon Prommueangma (Average M1+M2) | D9: =AVERAGE(D4:D5) -> 10.844618 | E9: HAE-MBB
A10: Slide 7 | B10: Performance by PE Owner: Palagon (HAE) | C10: Palagon Prommueangma (Average M1+M2) | D10: =AVERAGEIF('2026'!R:R,"Palagon Prommueangma",'2026'!BD:BD) -> 4 | E10: HAE-MBB
A11: Slide 7 | B11: Performance by PE Owner: Palagon (TME) | C11: Palagon Prommueangma ((Average M1+M2) | D11: 5.37 | E11: TME-MBB | F11: 1.66 | G11: 2.3

Sheet Part 3 - Doc Management
A1: Slide No | B1: Slide Title | C1: Owner / Type | D1: Amount (THB) | E1: Done (THB) | F1: Avg Aging | G1: Notes
A2: Slide 8 | B2: Overall Team Install WK35 | C2: Overall Team Install WK35 | D2: 145006 | F2: 6 | G2: จำนวนงานติดตั้ง Completed WEEK 34
A3: Slide 8 | B3: Overall Team Install WK36 | C3: Overall Team Install WK36 | D3: 73027 | F3: 3 | G3: จำนวนงานติดตั้ง Completed WEEK 36
A4: Slide 9 | B4: DOC Owner: Hathairat Singkaew | C4: Hathairat (MBB/HAE) | F4: =AVERAGEIF('2026'!S:S, "น.ส. หทัยรัตน์ สิงห์แก้ว",'2026'!BE:BE) -> 8.2592593 | G4: จำนวนงานที่ค้างส่งและ Aging เฉลี่ย
A5: Slide 9 | B5: DOC Owner: Sermsiri Bampentam | C5: Sermsiri (IPRAN/TME) | F5: =AVERAGEIF('2026'!S:S, "Sermsiri Bampentam",'2026'!BE:BE) -> 14 | G5: เจาะลึกงาน IPRAN/TME
A6: Slide 9 | B6: DOC Owner: Apichart Kampuang | C6: Apichart (MBB/HAE) | F6: =AVERAGEIF('2026'!S:S, "Apichart Kampuang",'2026'!BE:BE) -> 5.7586207 | G6: ภาพรวมงาน MBB/HAE
A7: Slide 10 | B7: Acceptance AC#1 Performance | C7: AC#1 (JAN-DEC) | D7: ='2026'!AB2*0.7 -> 3694342 | E7: ='2026'!BH2 -> 3385456.3 | F7: =AVERAGE('2026'!BJ4:BJ258) -> 14.301653
A8: Slide 10 | B8: Acceptance AC#2 Performance | C8: AC#2 (JAN-DEC) | D8: ='2026'!AB2*0.3 -> 1583289.4 | E8: ='2026'!BK2 -> 782067.08 | F8: =AVERAGE('2026'!BM4:BM258) -> 58.412037
A9: Slide 11 | B9: Work Type Analysis | C9: MBB vs IPRAN | G9: เปรียบเทียบความคล่องตัวในการปิดเอกสาร

Sheet Part 4 - Financials
A1: Slide No | B1: Slide Title | C1: Metric | D1: Value (THB) | E1: Notes
A2: Slide 12 | B2: Financial Health Overview | C2: Estimate Final Income | D2: ='2026'!AB2 -> 5277631.4 | E2: ภาพรวมรายได้ประมาณการ
A3: Slide 12 | B3: AR vs AP (Economic Efficiency) | C3: AR (Commerce) | D3: ='2026'!AR2 -> 1916244.1 | E3: วิเคราะห์ส่วนต่าง (Margin)
A4: Slide 12 | B4: AR vs AP (Economic Efficiency) | C4: AP (Payment) | D4: ='2026'!AS2 -> 540628.5 | E4: สถานะการเบิกจ่าย Subcontractors
A5: Slide 12 | B5: Unfulfilled Revenue (Remain) | C5: Remain to Claim | D5: =D2-(D3+D4) -> 2820758.8 | E5: เม็ดเงินที่หายไปชั่วคราว
A6: Slide 13 | B6: Backlog Backlog Week 35 VS Backlog Week 36 | C6: Backlog Week 35 | D6: =Sheet1!N10 -> 1529546.1 | E6: เปรียบเทียบเป้าหมายการเก็บเงินระหว่างสัปดาห์
A7: Slide 13 | B7: Backlog Backlog Week 35 VS Backlog Week 36 | C7: Backlog Week 36 | D7: =Sheet1!N20 -> 1362832.1 | E7: กราฟเส้นแนวโน้มยอดคงค้าง
A8: Slide 14 | B8: Actual Acceptance WK32 | C8: Actual Acceptance WK32 | D8: 200182.15 | E8: ยอด Actual Acceptance WK32
A9: Slide 14 | B9: Actual Acceptance WK33 | C9: Actual Acceptance WK33 | D9: 574611.8 | E9: ยอด Actual Acceptance WK33
A10: Slide 14 | B10: Actual Acceptance WK34 | C10: Actual Acceptance WK34 | D10: 321841.3 | E10: ยอด Actual Acceptance WK34
A11: Slide 14 | B11: Actual Acceptance WK35 | C11: Actual Acceptance WK35 | D11: 390171.6 | E11: ยอด Actual Acceptance WK35
A12: Slide 14 | B12: Actual Acceptance WK36 | C12: Actual Acceptance WK36 | D12: 346396.4 | E12: ยอด Actual Acceptance WK36
A13: Slide 15 | B13: Actual Acceptance TOTAL (JAN-AUGUST) HUAWEI | C13: Actual Acceptance TOTAL (JAN-AUGUST) HUAWEI | D13: 6126104.7 | E13: ยอด Actual Actual Acceptance TOTAL (JAN-AUGUST) HUAWEI
A14: Slide 15 | B14: Actual Acceptance TOTAL (JAN-AUGUST) TRUE-TUC | C14: Actual Acceptance TOTAL (JAN-AUGUST) TRUE-TUC | D14: 6982082.2 | E14: ยอด Actual Actual Acceptance TOTAL (JAN-AUGUST) TRUE-TUC
A15: Slide 16 | B15: Plan: Action Plan AC#1 WK36 | C15: Action Plan AC#1 WK36 | D15: 182483 | E15: Action Plan AC#1 WK35
A16: Slide 16 | B16: Plan: Action Plan AC#2 WK36 | C16: Action Plan AC#2 WK36 | D16: 139847.4 | E16: Action Plan AC#2 WK35
A17: Slide 16 | B17: Plan: Action Plan TOTAL WK36 | C17: Action Plan TOTAL WK36 | D17: =SUM(D15:D16) -> 322330.4 | E17: Action Plan TOTAL WK35
A18: Slide 17 | B18: Plan: Acceptance AC#1 Plan WK36 (2023) | C18: Action Plan AC#1 WK36 | D18: =Sheet1!R27 -> 0 | E18: ยอด Remain ที่ตั้งเป้าจะเคลียร์ (2023)
A19: Slide 17 | B19: Plan: Acceptance AC#1 Plan WK36 (2024) | C19: Action Plan AC#1 WK36 | D19: =Sheet1!R28 -> 0 | E19: ยอด Remain ที่ตั้งเป้าจะเคลียร์ (2024)
A20: Slide 17 | B20: Plan: Acceptance AC#1 Plan WK36 (2025) | C20: Action Plan AC#1 WK36 | D20: =Sheet1!R29 -> 0 | E20: ยอด Remain ที่ตั้งเป้าจะเคลียร์ (2025)
A21: Slide 17 | B21: Plan: Acceptance AC#1 Plan WK36 (2026) | C21: Action Plan AC#1 WK36 | D21: 85350.3 | E21: ยอด Remain ที่ตั้งเป้าจะเคลียร์ (2026)
A22: Slide 17 | B22: Plan: Acceptance AC#1 Plan WK36 (TOTAL) | C22: Action Plan AC#1 WK 36 TOTAL | D22: =SUM(D18:D21) -> 85350.3 | E22: ยอด Remain Plan AC#1 WK 30 Total Amount
A23: Slide 18 | B23: Plan: Acceptance AC#2 Plan WK36 (2023) | C23: Action Plan AC#2 WK36 | D23: =Sheet1!R32 -> 0 | E23: ยอด Remain ที่ตั้งเป้าจะเคลียร์ (2023)
A24: Slide 18 | B24: Plan: Acceptance AC#2 Plan WK36 (2024) | C24: Action Plan AC#2 WK36 | D24: =Sheet1!R33 -> 0 | E24: ยอด Remain ที่ตั้งเป้าจะเคลียร์ (2024)
A25: Slide 18 | B25: Plan: Acceptance AC#2 Plan WK36 (2025) | C25: Action Plan AC#2 WK36 | E25: ยอด Remain ที่ตั้งเป้าจะเคลียร์ (2025)
A26: Slide 18 | B26: Plan: Acceptance AC#2 Plan WK36 (2026) | C26: Action Plan AC#2 WK36 | D26: 68127.6 | E26: ยอด Remain ที่ตั้งเป้าจะเคลียร์ (2026)
A27: Slide 18 | B27: Plan: Acceptance AC#2 Plan WK36 (TOTAL) | C27: Action Plan AC#2 WK36 TOTAL | D27: =SUM(D23:D26) -> 68127.6 | E27: แผนผลักดัน Plan AC#2 WK30 Total Amount
A28: Slide 19 | B28: Recovery Plan: Install On-Process | C28: On-Process (2026) TME-MBB | D28: =SUMIF('2026'!BP:BP,'Part 4 - Financials'!F28&'Part 4 - Financials'!G28,'2026'!AB:AB) -> 501518 | E28: มูลค่างานที่อยู่ระหว่างดำเนินการ | F28: TME | G28: MBB
A29: Slide 19 | B29: Recovery Plan: Install On-Process | C29: On-Process (2026) TME-IPRAN | D29: =SUMIF('2026'!BP:BP,'Part 4 - Financials'!F29&'Part 4 - Financials'!G29,'2026'!AB:AB) -> 225486.4 | E29: มูลค่างานที่อยู่ระหว่างดำเนินการ | F29: TME | G29: IPRAN
A30: Slide 19 | B30: Recovery Plan: Install On-Process | C30: On-Process (2026) TME-BATTERY | D30: =SUMIF('2026'!BP:BP,'Part 4 - Financials'!F30&'Part 4 - Financials'!G30,'2026'!AB:AB) -> 10214 | E30: มูลค่างานที่อยู่ระหว่างดำเนินการ | F30: TME | G30: BATERRY
A31: Slide 19 | B31: Recovery Plan: Install On-Process | C31: On-Process (2026) HAE-MBB | D31: =SUMIF('2026'!BP:BP,'Part 4 - Financials'!F31&'Part 4 - Financials'!G31,'2026'!AB:AB) -> 4540413 | E31: มูลค่างานที่อยู่ระหว่างดำเนินการ | F31: HAE | G31: MBB
A32: Slide 19 | B32: Recovery Plan: Install On-Process | C32: On-Process (2026) TRE-DISMANTLE | D32: =SUMIF('2026'!BP:BP,'Part 4 - Financials'!F32&'Part 4 - Financials'!G32,'2026'!AB:AB) -> 0 | E32: มูลค่างานที่อยู่ระหว่างดำเนินการ | F32: TRE | G32: DISMANTLE
A33: Slide 20 | B33: AC1 DONE (2023) REMAIN | C33: AC1 DONE REMAIN/ Total | D33: =Sheet1!E16 -> 25739.04 | E33: ยอด Remain ที่ตั้งเป้าจะเคลียร์ (2023)
A34: Slide 20 | B34: AC1 DONE (2024) REMAIN | C34: AC1 DONE REMAIN/ Total | D34: =Sheet1!E17 -> 7724.43 | E34: ยอด Remain ที่ตั้งเป้าจะเคลียร์ (2024)
A35: Slide 20 | B35: AC1 DONE (2025) REMAIN | C35: AC1 DONE REMAIN/ Total | D35: =Sheet1!E18 -> 27600 | E35: ยอด Remain ที่ตั้งเป้าจะเคลียร์ (2025)
A36: Slide 20 | B36: AC1 DONE (2026) REMAIN | C36: AC1 DONE REMAIN/ Total | D36: =Sheet1!E19 -> 142200.5 | E36: ยอด Remain ที่ตั้งเป้าจะเคลียร์ (2026)
A37: Slide 20 | B37: UNFULFILL (2023) REMAIN | C37: UNFULFILL REMAIN / Total | D37: =Sheet1!K16 -> 112782 | E37: ยอด Remain ที่ตั้งเป้าจะเคลียร์ (2023)
A38: Slide 20 | B38: UNFULFILL (2024) REMAIN | C38: UNFULFILL REMAIN / Total | D38: =Sheet1!K17 -> 60400 | E38: ยอด Remain ที่ตั้งเป้าจะเคลียร์ (2024)
A39: Slide 20 | B39: UNFULFILL (2025) REMAIN | C39: UNFULFILL REMAIN / Total | D39: =Sheet1!K18 -> 57762 | E39: ยอด Remain ที่ตั้งเป้าจะเคลียร์ (2025)
A40: Slide 20 | B40: UNFULFILL (2026) REMAIN | C40: UNFULFILL REMAIN / Total | D40: =Sheet1!K19 -> 768097 | E40: ยอด Remain ที่ตั้งเป้าจะเคลียร์ (2026)
A41: Slide 20 | B41: Summary of REMAIN (3 Pillars) | C41: Summary of REMAIN (3 Pillars) | D41: =SUM(D33:D40) -> 1202305
A42: Slide 21 | B42: Acceptane Target Plan JULY | C42: Acceptane Target Plan AUGUST | D42: 977310.28 | E42: Acceptane Target Plan AUGUST
A43: Slide 21 | B43: Acceptane Target Actual JULY | C43: Acceptane Target Actual AUGUST | D43: =SUM(D8:D12) -> 1833203.2 | E43: Acceptane Target Actual AUGUST

Sheet Part 5 - Safety
A1: Slide No | B1: Slide Title | C1: Topic / Metric | E1: Status / Detail

Sheet Part 7 - SLA On-Process AIS
A1: EXECUTIVE SUMMARY: SMART QC | E1: EXECUTIVE SUMMARY: PAT SUBCON SUBMIT
A2: สถานะงาน | B2: จำนวนไซต์ | C2: Aging เฉลี่ย (วัน) | E2: สถานะงาน | F2: จำนวนไซต์ | G2: Aging เฉลี่ย (วัน)
A3: 🟢 ปิดตามกำหนด (Done in SLA) | B3: 136 | C3: 1 | E3: 🟢 ส่งตามกำหนด (Done in SLA) | F3: 119 | G3: 3.2
A4: 🟡 ปิดงานล่าช้า (Done Late) | B4: 63 | C4: 6.7 | E4: 🟡 ส่งงานล่าช้า (Done Late) | F4: 80 | G4: 10.7
A5: 🔵 รอตรวจสอบ (Pending in SLA) | B5: 0 | C5: 0 | E5: 🔵 รอส่งงาน (Pending in SLA) | F5: 0 | G5: 0
A6: 🔴 ปิดเกินกำหนด / ค้างวิกฤต (Over SLA) | B6: 0 | C6: 0 | E6: 🔴 ปิดเกินกำหนด / ค้างวิกฤต (Over SLA) | F6: 0 | G6: 0
A22: ACTION REQUIRED: SMART QC | E22: ACTION REQUIRED: PAT SUBCON | G22: OWNER DOC | I22: REWORK REQUIRED: PAT NOT PASS | K22: OWNER DOC
A23: Site DUID | B23: Aging | E23: Site DUID | F23: Aging | G23: Assign | I23: Site DUID | J23: Aging | K23: Assign
A24: All sites are up to date 🎉 | E24: All sites are up to date 🎉 | G24: - | I24: PKFAM_2026 Capacity Expansion Ph1_EXP_ER | J24: 15 วัน | K24: น.ส. วราพร วงค์พิพันธ์
I25: NKNVM_2026 Capacity Expansion Modernize_EXP_ER | J25: 1 วัน | K25: Apichart Kampuang
I26: NVPSM_2026 Capacity Expansion Modernize_EXP_ER | J26: 1 วัน | K26: Apichart Kampuang
I27: NYOAM_2026 Capacity Expansion Modernize_EXP_ER | J27: 1 วัน | K27: Apichart Kampuang
I28: PMCDM_2026 Capacity Expansion Modernize_EXP_ER | J28: 1 วัน | K28: Apichart Kampuang
I29: SPOCM_2026 Capacity Expansion Modernize_EXP_ER | J29: 2 วัน | K29: น.ส. หทัยรัตน์ สิงห์แก้ว
I30: LPCTM_2026 Capacity Expansion Modernize_EXP_ER | J30: 1 วัน | K30: Apichart Kampuang
I31: TBKBM_2026 Capacity Expansion Modernize_EXP_ER | J31: 2 วัน | K31: น.ส. หทัยรัตน์ สิงห์แก้ว

Sheet Part 7 - SLA On-Process TRUE
A1: EXECUTIVE SUMMARY: SMART QC | E1: EXECUTIVE SUMMARY: PAT SUBCON SUBMIT
A2: สถานะงาน | B2: จำนวนไซต์ | C2: Aging เฉลี่ย (วัน) | E2: สถานะงาน | F2: จำนวนไซต์ | G2: Aging เฉลี่ย (วัน)
A3: 🟢 ปิดตามกำหนด (Done in SLA) | B3: 9 | C3: 1.1 | E3: 🟢 ส่งตามกำหนด (Done in SLA) | F3: 14 | G3: 2.1
A4: 🟡 ปิดงานล่าช้า (Done Late) | B4: 8 | C4: 9.1 | E4: 🟡 ส่งงานล่าช้า (Done Late) | F4: 2 | G4: 8.5
A5: 🔵 รอตรวจสอบ (Pending in SLA) | B5: 1 | C5: 1 | E5: 🔵 รอส่งงาน (Pending in SLA) | F5: 1 | G5: 4
A6: 🔴 ปิดเกินกำหนด / ค้างวิกฤต (Over SLA) | B6: 0 | C6: 0 | E6: 🔴 ปิดเกินกำหนด / ค้างวิกฤต (Over SLA) | F6: 0 | G6: 0
A22: ACTION REQUIRED: SMART QC | E22: ACTION REQUIRED: PAT SUBCON | G22: OWNER DOC | I22: REWORK REQUIRED: ALARM FOUND | K22: OWNER DOC
A23: Site DUID | B23: Aging | E23: Site DUID | F23: Aging | G23: Assign | I23: Site DUID | J23: Aging | K23: Assign
A24: CBR1005_Flash_RAN_EAS R3 | B24: 1 วัน | E24: CBR7972_Flash_RAN_EAS R3 | F24: 4 วัน | G24: GSC HW | I24: No rework required 🎉 | K24: -

Sheet 2026
A1: PM | B1: PM | C1: PM | D1: PM | E1: PM | F1: PM | G1: PM | H1: PM | I1: PM | J1: PM | K1: PM | L1: PM | M1: PM | O1: PM | P1: PM | Q1: PM | R1: PM | S1: PM | T1: PM | U1: PM | V1: PM | W1: PM | X1: PM | Y1: PM | Z1: PM | AA1: PM | AB1: PM | AC1: PM | AD1: CPO | AE1: CPO | AF1: CPO | AG1: CPO | AH1: CPO | AI1: CPO | AJ1: CPO | AK1: CPO | AL1: CPO | AM1: CPO | AN1: CPO | AO1: CPO | AP1: CPO | AQ1: CPO | AR1: ACCOUNT | AS1: ACCOUNT | AT1: PM | AU1: PM | AV1: PM | AW1: PM | AX1: CPO | AY1: CPO | AZ1: CPO | BA1: CPO
A2: 321 | B2: 324 | C2: 324 | D2: 4177505.1 | E2: 5109575.4 | F2: 324 | G2: 324 | H2: 324 | I2: 324 | J2: 324 | K2: 324 | L2: 299 | M2: 298 | O2: 299 | P2: 299 | Q2: 299 | R2: 298 | S2: 297 | T2: 322 | U2: 177503 | V2: 3895855.4 | W2: 113980 | X2: 854220 | Y2: 5041558.4 | Z2: 236073 | AA2: 313 | AB2: 5277631.4 | AC2: 3289682.9 | AD2: 798466.12 | AE2: 1123786.1 | AF2: 37800 | AG2: 3000 | AH2: 233 | AI2: 233 | AJ2: 233 | AK2: 1930 | AL2: 2053294.4 | AM2: 1422927.5 | AN2: 266045.24 | AO2: 1688972.8 | AP2: 453866.5 | AQ2: 458068.7 | AR2: 1916244.1 | AS2: 540628.5 | AT2: 175871.77 | AU2: 297 | AV2: 295 | AW2: 320 | AX2: 0 | AY2: 0 | BA2: 0 | BH2: 3385456.3 | BK2: 782067.08 | BN2: 4167523.4 | BO2: 1113252
A3: WON CODE | B3: WON NAME | C3: SITE/DUID | D3: Estimate Plan | E3: Estimate income | F3: Period WON | G3: Project | H3: Phase | I3: Site | J3: PMOwner | K3: Region | L3: Installation | M3: On-Service | N3: MONTH | O3: Subcon | P3: Subcon Account | Q3: TYPE SUB | R3: PE Owner | S3: DOC Owner | T3: WK NUM | U3: SO Survey | V3: SO Service | W3: SO Material | X3: SO Logistics | Y3: SUM SO | Z3: ADDITIONAL WORK | AA3: VO Submit Date | AB3: ESTIMATE FINAL INCOME | AC3: DLPlan | AD3: DLPRPO | AE3: SERVICE | AF3: DOC | AG3: OTHER | AH3: DL END Y/N/OTHER | AI3: PR END Y/N | AJ3: PO END Y/N | AK3: CREDIT NOTE | AL3: SO GGD | AM3: SO AC1 | AN3: SO AC2 | AO3: SO SAP | AP3: PR SUM | AQ3: PO APPROVED | AR3: AR | AS3: AP | AT3: GR INHOUSE | AU3: 1st Milestone | AV3: 2nd Milestone | AW3: 3rd Milestone | AX3: ACCRUE REV | AY3: ACCRUE DL | AZ3: CUSTOMER | BA3: CHECK | BB3: REMARK | BC3: SAP CODE | BD3: AGING 1st Milestone | BE3: AGING 2nd Milestone | BF3: STATUS WORK | BG3: WORK TYPE | BH3: Accaptance AC#1 AMOUNT | BI3: Accaptance AC#1 DONE | BJ3: AGING#1 | BK3: Accaptance AC#2 AMOUNT | BL3: Accaptance AC#2 DONE | BM3: AGING#2 | BN3: SUM AMOUT | BO3: REMAIN
A4: 29753 | B4: HAE-Cap_Q126-TBKDM | C4: TBKDM_2025 Capacity Expansion Ph8_EXP_ER | D4: 14999.6 | E4: 18293 | F4: 46023 | G4: HAE | H4: Cap_Q126 | I4: TBKDM | J4: BOONCHOT BORIWUT | K4: ER | L4: 46041 | M4: 46041 | N4: 46041 | O4: INHOUSE Adirek Kong-ang | P4: - | Q4: INHOUSE | R4: Adisak Chanmao | S4: น.ส. หทัยรัตน์ สิงห์แก้ว | T4: 26WK4 | U4: 793 | V4: 10758 | W4: 2579 | X4: 4163 | Y4: 18293 | Z4: 0 | AA4: - | AB4: 18293 | AC4: 30477.6 | AD4: 300 | AE4: 300 | AF4: 300 | AG4: 0 | AH4: Y | AI4: Y | AJ4: Y | AK4: 0 | AL4: 18293 | AM4: 15065.6 | AN4: 3227.4 | AO4: 18293 | AP4: 300 | AQ4: 300 | AR4: 18293 | AS4: 300 | AT4: 1352 | AU4: 46046 | AV4: 46050 | AW4: - | AX4: 0 | AY4: 0 | AZ4: HUAWEI | BD4: 5 | BE4: 9 | BF4: COMPLETED | BG4: MBB | BH4: 15065.6 | BI4: 46055 | BJ4: 14 | BK4: 3227.4 | BL4: 46081 | BM4: 40 | BN4: 18293 | BO4: 0 | BP4: =G4&BG4 -> HAEMBB
A5: 29754 | B5: HAE-Cap_Q126-TLRPM | C5: TLRPM_2025 Capacity Expansion Ph8_EXP_ER | D5: 10631.2 | E5: 12966 | F5: 46023 | G5: HAE | H5: Cap_Q126 | I5: TLRPM | J5: BOONCHOT BORIWUT | K5: ER | L5: 46041 | M5: 46041 | N5: 46041 | O5: INHOUSE PHET SAITHONG | P5: - | Q5: INHOUSE | R5: Adisak Chanmao | S5: Adisak Chanmao | T5: 26WK4 | U5: 793 | V5: 8008 | W5: 2579 | X5: 1586 | Y5: 12966 | Z5: 4453 | AA5: 46076 | AB5: 17419 | AC5: 30477.6 | AD5: 300 | AE5: 300 | AF5: 300 | AG5: 0 | AH5: Y | AI5: Y | AJ5: Y | AK5: 0 | AL5: 20062 | AM5: 16496.4 | AN5: 3036.6 | AO5: 19533 | AP5: 300 | AQ5: 300 | AR5: 19533 | AS5: 300 | AT5: 1352 | AU5: 46044 | AV5: 46050 | AW5: - | AX5: 529 | AY5: 0 | AZ5: HUAWEI | BD5: 3 | BE5: 9 | BF5: COMPLETED | BG5: MBB | BH5: 16866.7 | BI5: 46055 | BJ5: 14 | BK5: 3195.3 | BL5: 46081 | BM5: 40 | BN5: 20062 | BO5: 0 | BP5: =G5&BG5 -> HAEMBB
A6: 29762 | B6: HAE-Cap_Q126-CPCEM | C6: CPCEM_2025 Capacity Expansion Ph8_EXP_ER | D6: 11391.4 | E6: 13892 | F6: 46023 | G6: HAE | H6: Cap_Q126 | I6: CPCEM | J6: BOONCHOT BORIWUT | K6: ER | L6: 46039 | M6: 46039 | N6: 46039 | O6: INHOUSE Adirek Kong-ang | P6: - | Q6: INHOUSE | R6: Adisak Chanmao | S6: น.ส. หทัยรัตน์ สิงห์แก้ว | T6: 26WK3 | U6: 793 | V6: 8934 | W6: 2579 | X6: 1586 | Y6: 13892 | Z6: 0 | AA6: - | AB6: 13892 | AC6: 30477.6 | AD6: 300 | AE6: 300 | AF6: 300 | AG6: 0 | AH6: Y | AI6: Y | AJ6: Y | AK6: 0 | AL6: 13892 | AM6: 11211.8 | AN6: 2680.2 | AO6: 13892 | AP6: 300 | AQ6: 300 | AR6: 13892 | AS6: 300 | AT6: 1352 | AU6: 46039 | AV6: 46043 | AW6: - | AX6: 0 | AY6: 0 | AZ6: HUAWEI | BD6: 0 | BE6: 4 | BF6: COMPLETED | BG6: MBB | BH6: 11211.8 | BI6: 46055 | BJ6: 16 | BK6: 2680.2 | BL6: 46081 | BM6: 42 | BN6: 13892 | BO6: 0 | BP6: =G6&BG6 -> HAEMBB
A7: 29763 | B7: HAE-Cap_Q126-WSNIM | C7: WSNIM_2025 Capacity Expansion Ph8_EXP_ER | D7: 19812.4 | E7: 24162 | F7: 46023 | G7: HAE | H7: Cap_Q126 | I7: WSNIM | J7: BOONCHOT BORIWUT | K7: ER | L7: 46038 | M7: 46038 | N7: 46038 | O7: นาย อภิชาติ ฟังสันเทียะ | P7: VD00235 | Q7: SUBCON | R7: Adisak Chanmao | S7: น.ส. หทัยรัตน์ สิงห์แก้ว | T7: 26WK3 | U7: 793 | V7: 16627 | W7: 2579 | X7: 4163 | Y7: 24162 | Z7: 4453 | AA7: 46051 | AB7: 28615 | AC7: 30477.6 | AD7: 11925 | AE7: 11625 | AF7: 300 | AG7: 0 | AH7: Y | AI7: Y | AJ7: Y | AK7: 0 | AL7: 31258 | AM7: 25477 | AN7: 5781 | AO7: 31258 | AP7: 11985 | AQ7: 11865 | AR7: 31258 | AS7: 11865 | AT7: 0 | AU7: 46039 | AV7: 46065 | AW7: - | AX7: 0 | AY7: 60 | AZ7: HUAWEI | BD7: 1 | BE7: 27 | BF7: COMPLETED | BG7: MBB | BH7: 25477 | BI7: 46055 | BJ7: 17 | BK7: 5781 | BL7: 46096 | BM7: 58 | BN7: 31258 | BO7: 0 | BP7: =G7&BG7 -> HAEMBB
A8: 29767 | B8: HAE-Cap_Q126-WNALM | C8: WNALM_2025 Capacity Expansion Ph8_EXP_ER | D8: 20809.8 | E8: 25379 | F8: 46023 | G8: HAE | H8: Cap_Q126 | I8: WNALM | J8: BOONCHOT BORIWUT | K8: ER | L8: 46041 | M8: 46041 | N8: 46041 | O8: นาย อภิชาติ ฟังสันเทียะ | P8: VD00235 | Q8: SUBCON | R8: Adisak Chanmao | S8: น.ส. หทัยรัตน์ สิงห์แก้ว | T8: 26WK4 | U8: 793 | V8: 17844 | W8: 2579 | X8: 4163 | Y8: 25379 | Z8: 792 | AA8: 46051 | AB8: 26171 | AC8: 30477.6 | AD8: 12235 | AE8: 11935 | AF8: 300 | AG8: 0 | AH8: Y | AI8: Y | AJ8: Y | AK8: 0 | AL8: 26171 | AM8: 20580.2 | AN8: 5590.8 | AO8: 26171 | AP8: 12235 | AQ8: 12235 | AR8: 26171 | AS8: 12235 | AT8: 0 | AU8: 46042 | AV8: 46045 | AW8: - | AX8: 0 | AY8: 0 | AZ8: HUAWEI | BD8: 1 | BE8: 4 | BF8: COMPLETED | BG8: MBB | BH8: 20580.2 | BI8: 46055 | BJ8: 14 | BK8: 5590.8 | BL8: 46081 | BM8: 40 | BN8: 26171 | BO8: 0 | BP8: =G8&BG8 -> HAEMBB
A9: 29725 | B9: HAE-Cap_Q425-WHCSM | C9: WHCSM_2024 Coverage Expansion ph.2_New Site-Relocate_ER | D9: 47237.74 | E9: 57607 | F9: 46023 | G9: HAE | H9: Cap_Q425 | I9: WHCSM | J9: BOONCHOT BORIWUT | K9: ER | L9: 46043 | M9: 46045 | N9: 46045 | O9: นาย อภิชาติ ฟังสันเทียะ | P9: VD00235 | Q9: SUBCON | R9: Adisak Chanmao | S9: น.ส. หทัยรัตน์ สิงห์แก้ว | T9: 26WK4 | U9: 793 | V9: 44914 | W9: 7737 | X9: 4163 | Y9: 57607 | Z9: 0 | AA9: - | AB9: 57607 | AC9: 35716.34 | AD9: 22685 | AE9: 22385 | AF9: 300 | AG9: 0 | AH9: Y | AI9: Y | AJ9: Y | AK9: 0 | AL9: 52955 | AM9: 40876.4 | AN9: 12078.6 | AO9: 52955 | AP9: 22685 | AQ9: 22685 | AR9: 52955 | AS9: 22685 | AT9: 0 | AU9: 46063 | AV9: 46068 | AW9: - | AX9: 0 | AY9: 0 | AZ9: HUAWEI | BD9: 18 | BE9: 23 | BF9: COMPLETED | BG9: MBB | BH9: 40876.4 | BI9: 46067 | BJ9: 22 | BK9: 12078.6 | BL9: 46087 | BM9: 42 | BN9: 52955 | BO9: 4652 | BP9: =G9&BG9 -> HAEMBB
A10: 29757 | B10: HAE-Cap_Q126-TLBIM | C10: TLBIM_2025 Capacity Expansion Ph8_EXP_ER | D10: 15368.6 | E10: 18743 | F10: 46023 | G10: HAE | H10: Cap_Q126 | I10: TLBIM | J10: BOONCHOT BORIWUT | K10: ER | L10: 46044 | M10: 46044 | N10: 46044 | O10: นาย อภิชาติ ฟังสันเทียะ | P10: VD00235 | Q10: SUBCON | R10: Adisak Chanmao | S10: น.ส. หทัยรัตน์ สิงห์แก้ว | T10: 26WK4 | U10: 793 | V10: 11208 | W10: 2579 | X10: 4163 | Y10: 18743 | Z10: 0 | AA10: - | AB10: 18743 | AC10: 11620.66 | AD10: 8040 | AE10: 7740 | AF10: 300 | AG10: 0 | AH10: Y | AI10: Y | AJ10: Y | AK10: 0 | AL10: 18743 | AM10: 15380.6 | AN10: 3362.4 | AO10: 18743 | AP10: 8040 | AQ10: 8040 | AR10: 18743 | AS10: 8040 | AT10: 0 | AU10: 46044 | AV10: 46048 | AW10: - | AX10: 0 | AY10: 0 | AZ10: HUAWEI | BD10: 0 | BE10: 4 | BF10: COMPLETED | BG10: MBB | BH10: 15380.6 | BI10: 46055 | BJ10: 11 | BK10: 3362.4 | BL10: 46081 | BM10: 37 | BN10: 18743 | BO10: 0 | BP10: =G10&BG10 -> HAEMBB
A11: 29758 | B11: HAE-Cap_Q126-KNBPM | C11: KNBPM_2025 Capacity Expansion Ph8_EXP_ER | D11: 22933.8 | E11: 27969 | F11: 46023 | G11: HAE | H11: Cap_Q126 | I11: KNBPM | J11: BOONCHOT BORIWUT | K11: ER | L11: 46047 | M11: 46048 | N11: 46048 | O11: นาย อภิชาติ ฟังสันเทียะ | P11: VD00235 | Q11: SUBCON | R11: Adisak Chanmao | S11: น.ส. หทัยรัตน์ สิงห์แก้ว | T11: 26WK5 | U11: 793 | V11: 20434 | W11: 2579 | X11: 4163 | Y11: 27969 | Z11: 4453 | AA11: 46076 | AB11: 32422 | AC11: 17340.78 | AD11: 13255 | AE11: 12955 | AF11: 300 | AG11: 0 | AH11: Y | AI11: Y | AJ11: Y | AK11: 0 | AL11: 32422 | AM11: 26291.8 | AN11: 6130.2 | AO11: 32422 | AP11: 13255 | AQ11: 13255 | AR11: 32422 | AS11: 13255 | AT11: 0 | AU11: 46051 | AV11: 46057 | AW11: - | AX11: 0 | AY11: 0 | AZ11: HUAWEI | BD11: 3 | BE11: 9 | BF11: COMPLETED | BG11: MBB | BH11: 26291.8 | BI11: 46061 | BJ11: 13 | BK11: 6130.2 | BL11: 46081 | BM11: 33 | BN11: 32422 | BO11: 0 | BP11: =G11&BG11 -> HAEMBB
A12: 29759 | B12: HAE-Cap_Q126-KPWTM | C12: KPWTM_2025 Capacity Expansion Ph8_EXP_ER | D12: 12961.6 | E12: 15808 | F12: 46023 | G12: HAE | H12: Cap_Q126 | I12: KPWTM | J12: BOONCHOT BORIWUT | K12: ER | L12: 46048 | M12: 46048 | N12: 46048 | O12: INHOUSE Adirek Kong-ang | P12: - | Q12: INHOUSE | R12: Adisak Chanmao | S12: น.ส. หทัยรัตน์ สิงห์แก้ว | T12: 26WK5 | U12: 793 | V12: 8273 | W12: 2579 | X12: 4163 | Y12: 15808 | Z12: 0 | AA12: - | AB12: 15808 | AC12: 9800.96 | AD12: 300 | AE12: 300 | AF12: 300 | AG12: 0 | AH12: Y | AI12: Y | AJ12: Y | AK12: 0 | AL12: 15808 | AM12: 13326.1 | AN12: 2481.9 | AO12: 15808 | AP12: 300 | AQ12: 300 | AR12: 15808 | AS12: 300 | AT12: 1352 | AU12: 46057 | AV12: 46060 | AW12: - | AX12: 0 | AY12: 0 | AZ12: HUAWEI | BD12: 9 | BE12: 12 | BF12: COMPLETED | BG12: MBB | BH12: 13326.1 | BI12: 46067 | BJ12: 19 | BK12: 2481.9 | BL12: 46081 | BM12: 33 | BN12: 15808 | BO12: 0 | BP12: =G12&BG12 -> HAEMBB
A13: 29760 | B13: HAE-Cap_Q126-CPTCM | C13: CPTCM_2025 Capacity Expansion Ph8_EXP_ER | D13: 15802.2 | E13: 19271 | F13: 46023 | G13: HAE | H13: Cap_Q126 | I13: CPTCM | J13: BOONCHOT BORIWUT | K13: ER | L13: 46046 | M13: 46046 | N13: 46046 | O13: INHOUSE PHET SAITHONG | P13: - | Q13: INHOUSE | R13: Adisak Chanmao | S13: น.ส. หทัยรัตน์ สิงห์แก้ว | T13: 26WK4 | U13: 793 | V13: 11736 | W13: 2579 | X13: 4163 | Y13: 19271 | Z13: 4453 | AA13: 46076 | AB13: 23724 | AC13: 11948.02 | AD13: 300 | AE13: 300 | AF13: 300 | AG13: 0 | AH13: Y | AI13: Y | AJ13: Y | AK13: 0 | AL13: 23724 | AM13: 20203.2 | AN13: 3520.8 | AO13: 23724 | AP13: 300 | AQ13: 300 | AR13: 23724 | AS13: 300 | AT13: 1352 | AU13: 46056 | AV13: 46063 | AW13: - | AX13: 0 | AY13: 0 | AZ13: HUAWEI | BD13: 10 | BE13: 17 | BF13: COMPLETED | BG13: MBB | BH13: 20203.2 | BI13: 46067 | BJ13: 21 | BK13: 3520.8 | BL13: 46096 | BM13: 50 | BN13: 23724 | BO13: 0 | BP13: =G13&BG13 -> HAEMBB
A14: 29761 | B14: HAE-Cap_Q126-BKWNM | C14: BKWNM_2025 Capacity Expansion Ph8_EXP_ER | D14: 20810.8 | E14: 25379 | F14: 46023 | G14: HAE | H14: Cap_Q126 | I14: BKWNM | J14: BOONCHOT BORIWUT | K14: ER | L14: 46046 | M14: 46046 | N14: 46046 | O14: นาย อภิชาติ ฟังสันเทียะ | P14: VD00235 | Q14: SUBCON | R14: Adisak Chanmao | S14: น.ส. หทัยรัตน์ สิงห์แก้ว | T14: 26WK4 | U14: 793 | V14: 17844 | W14: 2579 | X14: 4163 | Y14: 25379 | Z14: 0 | AA14: - | AB14: 25379 | AC14: 15734.98 | AD14: 11975 | AE14: 11675 | AF14: 300 | AG14: 0 | AH14: Y | AI14: Y | AJ14: Y | AK14: 0 | AL14: 25379 | AM14: 20025.8 | AN14: 5353.2 | AO14: 25379 | AP14: 11975 | AQ14: 11975 | AR14: 25379 | AS14: 11975 | AT14: 0 | AU14: 46047 | AV14: 46048 | AW14: - | AX14: 0 | AY14: 0 | AZ14: HUAWEI | BD14: 1 | BE14: 2 | BF14: COMPLETED | BG14: MBB | BH14: 20025.8 | BI14: 46055 | BJ14: 9 | BK14: 5353.2 | BL14: 46081 | BM14: 35 | BN14: 25379 | BO14: 0 | BP14: =G14&BG14 -> HAEMBB
A15: 29764 | B15: HAE-Cap_Q126-TTBPM | C15: TTBPM_2025 Capacity Expansion Ph8_EXP_ER | D15: 23694.2 | E15: 28896 | F15: 46023 | G15: HAE | H15: Cap_Q126 | I15: TTBPM | J15: BOONCHOT BORIWUT | K15: ER | L15: 46044 | M15: 46044 | N15: 46044 | O15: INHOUSE Adirek Kong-ang | P15: - | Q15: INHOUSE | R15: Adisak Chanmao | S15: น.ส. หทัยรัตน์ สิงห์แก้ว | T15: 26WK4 | U15: 793 | V15: 21361 | W15: 2579 | X15: 4163 | Y15: 28896 | Z15: 0 | AA15: - | AB15: 28896 | AC15: 17915.52 | AD15: 300 | AE15: 300 | AF15: 300 | AG15: 0 | AH15: Y | AI15: Y | AJ15: Y | AK15: 0 | AL15: 28896 | AM15: 22487.7 | AN15: 6408.3 | AO15: 28896 | AP15: 300 | AQ15: 300 | AR15: 28896 | AS15: 300 | AT15: 1352 | AU15: 46044 | AV15: 46046 | AW15: - | AX15: 0 | AY15: 0 | AZ15: HUAWEI | BD15: 0 | BE15: 2 | BF15: COMPLETED | BG15: MBB | BH15: 22487.7 | BI15: 46055 | BJ15: 11 | BK15: 6408.3 | BL15: 46081 | BM15: 37 | BN15: 28896 | BO15: 0 | BP15: =G15&BG15 -> HAEMBB
A16: 29766 | B16: HAE-Cap_Q126-WPNRM | C16: WPNRM_2025 Capacity Expansion Ph8_EXP_ER | D16: 11607.2 | E16: 14156 | F16: 46023 | G16: HAE | H16: Cap_Q126 | I16: WPNRM | J16: BOONCHOT BORIWUT | K16: ER | L16: 46044 | M16: 46044 | N16: 46044 | O16: INHOUSE PHET SAITHONG | P16: - | Q16: INHOUSE | R16: Adisak Chanmao | S16: น.ส. หทัยรัตน์ สิงห์แก้ว | T16: 26WK4 | U16: 793 | V16: 9198 | W16: 2579 | X16: 1586 | Y16: 14156 | Z16: 8906 | AA16: 46076 | AB16: 23062 | AC16: 8776.72 | AD16: 300 | AE16: 300 | AF16: 300 | AG16: 0 | AH16: Y | AI16: Y | AJ16: Y | AK16: 0 | AL16: 23062 | AM16: 20302.6 | AN16: 2759.4 | AO16: 23062 | AP16: 360 | AQ16: 240 | AR16: 23062 | AS16: 240 | AT16: 1352 | AU16: 46044 | AV16: 46045 | AW16: - | AX16: 0 | AY16: 60 | AZ16: HUAWEI | BD16: 0 | BE16: 1 | BF16: COMPLETED | BG16: MBB | BH16: 20302.6 | BI16: 46055 | BJ16: 11 | BK16: 2759.4 | BL16: 46081 | BM16: 37 | BN16: 23062 | BO16: 0 | BP16: =G16&BG16 -> HAEMBB
A17: 29755 | B17: HAE-Cap_Q126-PNTHM | C17: PNTHM_2025 Capacity Expansion Ph8_EXP_ER | D17: 20744.8 | E17: 25299 | F17: 46023 | G17: HAE | H17: Cap_Q126 | I17: PNTHM | J17: BOONCHOT BORIWUT | K17: ER | L17: 46053 | M17: 46053 | N17: 46053 | O17: INHOUSE Adirek Kong-ang | P17: - | Q17: INHOUSE | R17: Adisak Chanmao | S17: น.ส. หทัยรัตน์ สิงห์แก้ว | T17: 26WK5 | U17: 793 | V17: 17764 | W17: 2579 | X17: 4163 | Y17: 25299 | Z17: 4453 | AA17: 46076 | AB17: 29752 | AC17: 15685.38 | AD17: 300 | AE17: 300 | AF17: 300 | AG17: 0 | AH17: Y | AI17: Y | AJ17: Y | AK17: 0 | AL17: 29752 | AM17: 24422.8 | AN17: 5329.2 | AO17: 29752 | AP17: 300 | AQ17: 300 | AR17: 29752 | AS17: 300 | AT17: 1352 | AU17: 46063 | AV17: 46072 | AW17: - | AX17: 0 | AY17: 0 | AZ17: HUAWEI | BD17: 10 | BE17: 19 | BF17: COMPLETED | BG17: MBB | BH17: 24422.8 | BI17: 46081 | BJ17: 28 | BK17: 5329.2 | BL17: 46096 | BM17: 43 | BN17: 29752 | BO17: 0 | BP17: =G17&BG17 -> HAEMBB
A18: 29765 | B18: HAE-Cap_Q126-WTWAM | C18: WTWAM_2025 Capacity Expansion Ph8_EXP_ER | D18: 19184.2 | E18: 23396 | F18: 46023 | G18: HAE | H18: Cap_Q126 | I18: WTWAM | J18: BOONCHOT BORIWUT | K18: ER | L18: 46055 | M18: 46055 | N18: 46055 | O18: นาย อภิชาติ ฟังสันเทียะ | P18: VD00235 | Q18: SUBCON | R18: Adisak Chanmao | S18: น.ส. หทัยรัตน์ สิงห์แก้ว | T18: 26WK6 | U18: 793 | V18: 15861 | W18: 2579 | X18: 4163 | Y18: 23396 | Z18: 0 | AA18: - | AB18: 23396 | AC18: 14505.52 | AD18: 11555 | AE18: 11255 | AF18: 300 | AG18: 0 | AH18: Y | AI18: Y | AJ18: Y | AK18: 0 | AL18: 23396 | AM18: 18637.7 | AN18: 4758.3 | AO18: 23396 | AP18: 11615 | AQ18: 11495 | AR18: 23396 | AS18: 11495 | AT18: 0 | AU18: 46057 | AV18: 46065 | AW18: - | AX18: 0 | AY18: 60 | AZ18: HUAWEI | BD18: 2 | BE18: 10 | BF18: COMPLETED | BG18: MBB | BH18: 18637.7 | BI18: 46067 | BJ18: 12 | BK18: 4758.3 | BL18: 46096 | BM18: 41 | BN18: 23396 | BO18: 0 | BP18: =G18&BG18 -> HAEMBB
A19: EP26010018 | B19: HAE-NEWSITE-SHTLM | C19: SHTLM_2024 Coverage Expansion ph.2_New Site-Relocate_ER | D19: 22252.34 | E19: 27137 | F19: 46023 | G19: HAE | H19: NEWSITE | I19: SHTLM | J19: BOONCHOT BORIWUT | K19: ER | L19: 46049 | M19: 46053 | N19: 46053 | O19: INHOUSE PHET SAITHONG | P19: - | Q19: INHOUSE | R19: Adisak Chanmao | S19: น.ส. หทัยรัตน์ สิงห์แก้ว | T19: 26WK5 | U19: 793 | V19: 22179 | W19: 2579 | X19: 1586 | Y19: 27137 | Z19: 5024 | AA19: 46076 | AB19: 32161 | AC19: 16824.94 | AD19: 300 | AE19: 0 | AF19: 300 | AG19: 0 | AH19: Y | AI19: Y | AJ19: Y | AK19: 0 | AL19: 32161 | AM19: 6622.6 | AN19: 713.4 | AO19: 7336 | AP19: 300 | AQ19: 300 | AR19: 7336 | AS19: 300 | AT19: 6760 | AU19: 46059 | AV19: 46063 | AW19: - | AX19: 24825 | AY19: 0 | AZ19: HUAWEI | BD19: 6 | BE19: 10 | BF19: COMPLETED | BG19: MBB | BH19: 10139.4 | BI19: 46067 | BJ19: 14 | BK19: 2220.6 | BL19: 46087 | BM19: 34 | BN19: 12360 | BO19: 0 | BP19: =G19&BG19 -> HAEMBB
A20: EP26020021 | B20: TME-DIS_ATN-RYG0118 | C20: RYG0118-AC-02_D_Dismantle_EAST_R3 | D20: 1687.29 | E20: 2081 | F20: 46054 | G20: TME | H20: DIS_ATN | I20: RYG0118 | J20: BOONCHOT BORIWUT | K20: ER | L20: 46051 | M20: 46051 | N20: 46051 | O20: บริษัท สุพรรณ เทเลคอม จำกัด | P20: VD00327 | Q20: SUBCON | R20: Adisak Chanmao | S20: Sermsiri Bampentam | T20: 26WK5 | U20: 0 | V20: 1970 | W20: 0 | X20: 111 | Y20: 2081 | Z20: 0 | AA20: - | AB20: 2081 | AC20: 1500 | AD20: 1230 | AE20: 1230 | AF20: 0 | AG20: 0 | AH20: Y | AI20: Y | AJ20: Y | AK20: 0 | AL20: 2081 | AM20: 1687 | AN20: 0 | AO20: 1687 | AP20: 1230 | AQ20: 1230 | AR20: 1687 | AS20: 1230 | AT20: 0 | AU20: 46051 | AV20: 46065 | AW20: - | AX20: 394 | AY20: 0 | AZ20: HUAWEI | BD20: 0 | BE20: 14 | BF20: COMPLETED | BG20: IPRAN | BH20: 1687 | BI20: 46073 | BJ20: 22 | BK20: 394 | BL20: 46230 | BM20: 179 | BN20: 2081 | BO20: 0 | BP20: =G20&BG20 -> TMEIPRAN
A21: EP26020022 | B21: TME-DIS_ATN-RYG0146 | C21: RYG0146-AC-02_D_Dismantle_EAST_R3 | D21: 1687.29 | E21: 2081 | F21: 46054 | G21: TME | H21: DIS_ATN | I21: RYG0146 | J21: BOONCHOT BORIWUT | K21: ER | L21: 46051 | M21: 46051 | N21: 46051 | O21: บริษัท สุพรรณ เทเลคอม จำกัด | P21: VD00327 | Q21: SUBCON | R21: Adisak Chanmao | S21: Sermsiri Bampentam | T21: 26WK5 | U21: 0 | V21: 1970 | W21: 0 | X21: 111 | Y21: 2081 | Z21: 0 | AA21: - | AB21: 2081 | AC21: 1500 | AD21: 1230 | AE21: 1230 | AF21: 0 | AG21: 0 | AH21: Y | AI21: Y | AJ21: Y | AK21: 0 | AL21: 2081 | AM21: 1687 | AN21: 0 | AO21: 1687 | AP21: 1230 | AQ21: 1230 | AR21: 1687 | AS21: 1230 | AT21: 0 | AU21: 46051 | AV21: 46073 | AW21: - | AX21: 394 | AY21: 0 | AZ21: HUAWEI | BD21: 0 | BE21: 22 | BF21: COMPLETED | BG21: IPRAN | BH21: 1687 | BI21: 46073 | BJ21: 22 | BK21: 394 | BL21: 46230 | BM21: 179 | BN21: 2081 | BO21: 0 | BP21: =G21&BG21 -> TMEIPRAN
A22: EP26020023 | B22: TME-DIS_ATN-RYG0168 | C22: RYG0168-AC-02_D_Dismantle_EAST_R3 | D22: 1687.29 | E22: 2081 | F22: 46054 | G22: TME | H22: DIS_ATN | I22: RYG0168 | J22: BOONCHOT BORIWUT | K22: ER | L22: 46051 | M22: 46051 | N22: 46051 | O22: บริษัท สุพรรณ เทเลคอม จำกัด | P22: VD00327 | Q22: SUBCON | R22: Adisak Chanmao | S22: Sermsiri Bampentam | T22: 26WK5 | U22: 0 | V22: 1970 | W22: 0 | X22: 111 | Y22: 2081 | Z22: 0 | AA22: - | AB22: 2081 | AC22: 1500 | AD22: 1230 | AE22: 1230 | AF22: 0 | AG22: 0 | AH22: Y | AI22: Y | AJ22: Y | AK22: 0 | AL22: 2081 | AM22: 1687 | AN22: 0 | AO22: 1687 | AP22: 1230 | AQ22: 1230 | AR22: 1687 | AS22: 1230 | AT22: 0 | AU22: 46071 | AV22: 46073 | AW22: - | AX22: 394 | AY22: 0 | AZ22: HUAWEI | BD22: 20 | BE22: 22 | BF22: COMPLETED | BG22: IPRAN | BH22: 1687 | BI22: 46081 | BJ22: 30 | BK22: 394 | BL22: 46230 | BM22: 179 | BN22: 2081 | BO22: 0 | BP22: =G22&BG22 -> TMEIPRAN
A23: EP26020024 | B23: TME-DIS_ATN-RYG0083 | C23: RYG0083-AC-02_D_Dismantle_EAST_R3 | D23: 1687.29 | E23: 2081 | F23: 46054 | G23: TME | H23: DIS_ATN | I23: RYG0083 | J23: BOONCHOT BORIWUT | K23: ER | L23: 46052 | M23: 46052 | N23: 46052 | O23: บริษัท สุพรรณ เทเลคอม จำกัด | P23: VD00327 | Q23: SUBCON | R23: Adisak Chanmao | S23: Sermsiri Bampentam | T23: 26WK5 | U23: 0 | V23: 1970 | W23: 0 | X23: 111 | Y23: 2081 | Z23: 0 | AA23: - | AB23: 2081 | AC23: 1500 | AD23: 1230 | AE23: 1230 | AF23: 0 | AG23: 0 | AH23: Y | AI23: Y | AJ23: Y | AK23: 0 | AL23: 2081 | AM23: 1687 | AN23: 0 | AO23: 1687 | AP23: 1230 | AQ23: 1230 | AR23: 1687 | AS23: 1230 | AT23: 0 | AU23: 46052 | AV23: 46065 | AW23: - | AX23: 394 | AY23: 0 | AZ23: HUAWEI | BD23: 0 | BE23: 13 | BF23: COMPLETED | BG23: IPRAN | BH23: 1687 | BI23: 46073 | BJ23: 21 | BK23: 394 | BL23: 46230 | BM23: 178 | BN23: 2081 | BO23: 0 | BP23: =G23&BG23 -> TMEIPRAN
A24: EP26020025 | B24: TME-REPIPRAN-TRT0164 | C24: TRT0164_TRT3001_D_Retain_New_EAST_R3 | D24: 2736.06 | E24: 7468 | F24: 46054 | G24: TME | H24: REPIPRAN | I24: TRT0164 | J24: BOONCHOT BORIWUT | K24: ER | L24: 46052 | M24: 46052 | N24: 46052 | O24: นาย ชัชวาล เคราะห์ดี | P24: VD01205 | Q24: SUBCON | R24: Adisak Chanmao | S24: Sermsiri Bampentam | T24: 26WK5 | U24: 0 | V24: 2364 | W24: 1370 | X24: 0 | Y24: 3734 | Z24: 0 | AA24: - | AB24: 3734 | AC24: 2400 | AD24: 2230 | AE24: 2230 | AF24: 0 | AG24: 0 | AH24: Y | AI24: Y | AJ24: Y | AK24: 0 | AL24: 3734 | AM24: 3261.2 | AN24: 472.8 | AO24: 3734 | AP24: 2230 | AQ24: 2230 | AR24: 3734 | AS24: 1784 | AT24: 0 | AU24: 46051 | AV24: 46162 | AW24: - | AX24: 0 | AY24: 446 | AZ24: HUAWEI | BD24: 0 | BE24: 110 | BF24: COMPLETED | BG24: IPRAN | BH24: 3261.2 | BI24: 46073 | BJ24: 21 | BK24: 472.8 | BL24: 46213 | BM24: 161 | BN24: 3734 | BO24: 0 | BP24: =G24&BG24 -> TMEIPRAN
A25: EP26020026 | B25: TME-REPIPRAN-TRT0135 | C25: TRT0164_TRT0135_D_Retain_New_EAST_R3 | D25: 2736.06 | E25: 3734 | F25: 46054 | G25: TME | H25: REPIPRAN | I25: TRT0135 | J25: BOONCHOT BORIWUT | K25: ER | L25: 46052 | M25: 46052 | N25: 46052 | O25: นาย ชัชวาล เคราะห์ดี | P25: VD01205 | Q25: SUBCON | R25: Adisak Chanmao | S25: Sermsiri Bampentam | T25: 26WK5 | U25: 0 | V25: 2364 | W25: 1370 | X25: 0 | Y25: 3734 | Z25: 0 | AA25: - | AB25: 3734 | AC25: 2400 | AD25: 2230 | AE25: 2230 | AF25: 0 | AG25: 0 | AH25: Y | AI25: Y | AJ25: Y | AK25: 0 | AL25: 3734 | AM25: 3261.2 | AN25: 472.8 | AO25: 3734 | AP25: 2230 | AQ25: 2230 | AR25: 3734 | AS25: 1784 | AT25: 0 | AU25: 46051 | AV25: 46162 | AW25: - | AX25: 0 | AY25: 446 | AZ25: HUAWEI | BD25: 0 | BE25: 110 | BF25: COMPLETED | BG25: IPRAN | BH25: 3261.2 | BI25: 46073 | BJ25: 21 | BK25: 472.8 | BL25: 46213 | BM25: 161 | BN25: 3734 | BO25: 0 | BP25: =G25&BG25 -> TMEIPRAN
A26: EP26020003 | B26: HAE-Cap_Q126-NSCGM | C26: NSCGM_2025 Capacity Expansion Ph8_EXP_ER | D26: 19314.28 | E26: 23554 | F26: 46054 | G26: HAE | H26: Cap_Q126 | I26: NSCGM | J26: BOONCHOT BORIWUT | K26: ER | L26: 46059 | M26: 46059 | N26: 46059 | O26: INHOUSE PHET SAITHONG | P26: - | Q26: INHOUSE | R26: Adisak Chanmao | S26: น.ส. หทัยรัตน์ สิงห์แก้ว | T26: 26WK6 | U26: 793 | V26: 16019 | W26: 2579 | X26: 4163 | Y26: 23554 | Z26: 7535 | AA26: 46076 | AB26: 31089 | AC26: 14603.48 | AD26: 300 | AE26: 300 | AF26: 300 | AG26: 0 | AH26: Y | AI26: Y | AJ26: Y | AK26: 0 | AL26: 31089 | AM26: 26283.3 | AN26: 4805.7 | AO26: 31089 | AP26: 300 | AQ26: 300 | AR26: 31089 | AS26: 300 | AT26: 4710.8 | AU26: 46062 | AV26: 46069 | AW26: - | AX26: 0 | AY26: 0 | AZ26: HUAWEI | BD26: 3 | BE26: 10 | BF26: COMPLETED | BG26: MBB | BH26: 26283.3 | BI26: 46081 | BJ26: 22 | BK26: 4805.7 | BL26: 46096 | BM26: 37 | BN26: 31089 | BO26: 0 | BP26: =G26&BG26 -> HAEMBB
A27: EP26020005 | B27: HAE-Cap_Q126-MKAOM | C27: MKAOM_2025 Capacity Expansion Ph8_EXP_ER | D27: 13363.54 | E27: 16297 | F27: 46054 | G27: HAE | H27: Cap_Q126 | I27: MKAOM | J27: BOONCHOT BORIWUT | K27: ER | L27: 46057 | M27: 46057 | N27: 46057 | O27: นาย อภิชาติ ฟังสันเทียะ | P27: VD00235 | Q27: SUBCON | R27: Adisak Chanmao | S27: น.ส. หทัยรัตน์ สิงห์แก้ว | T27: 26WK6 | U27: 793 | V27: 11339 | W27: 2579 | X27: 1586 | Y27: 16297 | Z27: 792 | AA27: 46076 | AB27: 17089 | AC27: 10104.14 | AD27: 8790 | AE27: 8490 | AF27: 300 | AG27: 0 | AH27: Y | AI27: Y | AJ27: Y | AK27: 1137 | AL27: 17089 | AM27: 13449.7 | AN27: 3639.3 | AO27: 17089 | AP27: 8790 | AQ27: 8790 | AR27: 17089 | AS27: 8790 | AT27: 0 | AU27: 46062 | AV27: 46066 | AW27: - | AX27: 0 | AY27: 0 | AZ27: HUAWEI | BD27: 5 | BE27: 9 | BF27: COMPLETED | BG27: MBB | BH27: 13449.7 | BI27: 46081 | BJ27: 24 | BK27: 3639.3 | BL27: 46096 | BM27: 39 | BN27: 17089 | BO27: 0 | BP27: =G27&BG27 -> HAEMBB
A28: EP26020011 | B28: HAE-Cap_Q126-TPRTM | C28: TPRTM_2025 Capacity Expansion Ph8_EXP_ER | D28: 10481.24 | E28: 12782 | F28: 46054 | G28: HAE | H28: Cap_Q126 | I28: TPRTM | J28: BOONCHOT BORIWUT | K28: ER | L28: 46057 | M28: 46058 | N28: 46058 | O28: INHOUSE PHET SAITHONG | P28: - | Q28: INHOUSE | R28: Adisak Chanmao | S28: น.ส. หทัยรัตน์ สิงห์แก้ว | T28: 26WK6 | U28: 793 | V28: 7824 | W28: 2579 | X28: 1586 | Y28: 12782 | Z28: 1584 | AA28: 46076 | AB28: 14366 | AC28: 7924.84 | AD28: 300 | AE28: 300 | AF28: 300 | AG28: 0 | AH28: Y | AI28: Y | AJ28: Y | AK28: 0 | AL28: 15952 | AM28: 16353.3 | AN28: 4883.7 | AO28: 21237 | AP28: 300 | AQ28: 300 | AR28: 15952 | AS28: 300 | AT28: 2556.4 | AU28: 46068 | AV28: 46073 | AW28: - | AX28: 0 | AY28: 0 | AZ28: HUAWEI | BD28: 10 | BE28: 15 | BF28: COMPLETED | BG28: MBB | BH28: 16353.3 | BI28: 46081 | BJ28: 23 | BK28: 4883.7 | BL28: 46096 | BM28: 38 | BN28: 21237 | BO28: 0 | BP28: =G28&BG28 -> HAEMBB
A29: EP26020012 | B29: HAE-Cap_Q126-SUNGM | C29: SUNGM_2025 Capacity Expansion Ph8_EXP_ER | D29: 20659.08 | E29: 25194 | F29: 46054 | G29: HAE | H29: Cap_Q126 | I29: SUNGM | J29: BOONCHOT BORIWUT | K29: ER | L29: 46056 | M29: 46056 | N29: 46056 | O29: INHOUSE PHET SAITHONG | P29: - | Q29: INHOUSE | R29: Adisak Chanmao | S29: น.ส. หทัยรัตน์ สิงห์แก้ว | T29: 26WK6 | U29: 793 | V29: 17659 | W29: 2579 | X29: 4163 | Y29: 25194 | Z29: 0 | AA29: - | AB29: 25194 | AC29: 15620.28 | AD29: 300 | AE29: 300 | AF29: 300 | AG29: 0 | AH29: Y | AI29: Y | AJ29: Y | AK29: 0 | AL29: 25194 | AM29: 19896.3 | AN29: 5297.7 | AO29: 25194 | AP29: 300 | AQ29: 300 | AR29: 25194 | AS29: 300 | AT29: 5038.8 | AU29: 46064 | AV29: 46069 | AW29: - | AX29: 0 | AY29: 0 | AZ29: HUAWEI | BD29: 8 | BE29: 13 | BF29: COMPLETED | BG29: MBB | BH29: 19896.3 | BI29: 46081 | BJ29: 25 | BK29: 5297.7 | BL29: 46096 | BM29: 40 | BN29: 25194 | BO29: 0 | BP29: =G29&BG29 -> HAEMBB
A30: EP26020014 | B30: HAE-Cap_Q126-DKBKM | C30: DKBKM_2025 Capacity Expansion Ph8_EXP_ER | D30: 13179.04 | E30: 16072 | F30: 46054 | G30: HAE | H30: Cap_Q126 | I30: DKBKM | J30: BOONCHOT BORIWUT | K30: ER | L30: 46059 | M30: 46059 | N30: 46059 | O30: INHOUSE Adirek Kong-ang | P30: - | Q30: INHOUSE | R30: Adisak Chanmao | S30: น.ส. หทัยรัตน์ สิงห์แก้ว | T30: 26WK6 | U30: 793 | V30: 8537 | W30: 2579 | X30: 4163 | Y30: 16072 | Z30: 528 | AA30: 46076 | AB30: 16600 | AC30: 9964.64 | AD30: 300 | AE30: 300 | AF30: 300 | AG30: 0 | AH30: Y | AI30: Y | AJ30: Y | AK30: 0 | AL30: 16600 | AM30: 13880.5 | AN30: 2719.5 | AO30: 16600 | AP30: 360 | AQ30: 240 | AR30: 16600 | AS30: 240 | AT30: 3214.4 | AU30: 46059 | AV30: 46063 | AW30: - | AX30: 0 | AY30: 60 | AZ30: HUAWEI | BD30: 0 | BE30: 4 | BF30: COMPLETED | BG30: MBB | BH30: 13880.5 | BI30: 46067 | BJ30: 8 | BK30: 2719.5 | BL30: 46096 | BM30: 37 | BN30: 16600 | BO30: 0 | BP30: =G30&BG30 -> HAEMBB
A31: EP26020020 | B31: HAE-Cap_Q126-BPGYM | C31: BPGYM_2025 Capacity Expansion Ph8_EXP_ER | D31: 13179.04 | E31: 16072 | F31: 46054 | G31: HAE | H31: Cap_Q126 | I31: BPGYM | J31: BOONCHOT BORIWUT | K31: ER | L31: 46058 | M31: 46058 | N31: 46058 | O31: นาย อภิชาติ ฟังสันเทียะ | P31: VD00235 | Q31: SUBCON | R31: Adisak Chanmao | S31: น.ส. หทัยรัตน์ สิงห์แก้ว | T31: 26WK6 | U31: 793 | V31: 8537 | W31: 2579 | X31: 4163 | Y31: 16072 | Z31: 1056 | AA31: 46076 | AB31: 17128 | AC31: 9964.64 | AD31: 7320 | AE31: 7020 | AF31: 300 | AG31: 0 | AH31: Y | AI31: Y | AJ31: Y | AK31: 0 | AL31: 17128 | AM31: 14250.1 | AN31: 2877.9 | AO31: 17128 | AP31: 7380 | AQ31: 7260 | AR31: 17128 | AS31: 7260 | AT31: 0 | AU31: 46063 | AV31: 46066 | AW31: - | AX31: 0 | AY31: 60 | AZ31: HUAWEI | BD31: 5 | BE31: 8 | BF31: COMPLETED | BG31: MBB | BH31: 14250.1 | BI31: 46081 | BJ31: 23 | BK31: 2877.9 | BL31: 46087 | BM31: 29 | BN31: 17128 | BO31: 0 | BP31: =G31&BG31 -> HAEMBB
A32: EP26020001 | B32: HAE-Cap_Q126-KHASM | C32: KHASM_2025 Capacity Expansion Ph8_EXP_ER | D32: 12810.86 | E32: 15623 | F32: 46066 | G32: HAE | H32: Cap_Q126 | I32: KHASM | J32: BOONCHOT BORIWUT | K32: ER | L32: 46063 | M32: 46063 | N32: 46063 | O32: INHOUSE Adirek Kong-ang | P32: - | Q32: INHOUSE | R32: Adisak Chanmao | S32: น.ส. หทัยรัตน์ สิงห์แก้ว | T32: 26WK7 | U32: 793 | V32: 8088 | W32: 2579 | X32: 4163 | Y32: 15623 | Z32: 1584 | AA32: 46076 | AB32: 17207 | AC32: 9686.26 | AD32: 300 | AE32: 300 | AF32: 300 | AG32: 0 | AH32: Y | AI32: Y | AJ32: Y | AK32: 0 | AL32: 17207 | AM32: 14305.4 | AN32: 2901.6 | AO32: 17207 | AP32: 300 | AQ32: 300 | AR32: 17207 | AS32: 240 | AT32: 3124.6 | AU32: 46072 | AV32: 46077 | AW32: - | AX32: 0 | AY32: 60 | AZ32: HUAWEI | BD32: 9 | BE32: 14 | BF32: COMPLETED | BG32: MBB | BH32: 14305.4 | BI32: 46087 | BJ32: 24 | BK32: 2901.6 | BL32: 46096 | BM32: 33 | BN32: 17207 | BO32: 0 | BP32: =G32&BG32 -> HAEMBB
A33: EP26020004 | B33: HAE-Cap_Q126-RSKBM | C33: RSKBM_2025 Capacity Expansion Ph8_EXP_ER | D33: 9765.38 | E33: 11909 | F33: 46066 | G33: HAE | H33: Cap_Q126 | I33: RSKBM | J33: BOONCHOT BORIWUT | K33: ER | L33: 46065 | M33: 46066 | N33: 46066 | O33: INHOUSE Adirek Kong-ang | P33: - | Q33: INHOUSE | R33: Adisak Chanmao | S33: น.ส. หทัยรัตน์ สิงห์แก้ว | T33: 26WK7 | U33: 793 | V33: 6951 | W33: 2579 | X33: 1586 | Y33: 11909 | Z33: 1452 | AA33: 46076 | AB33: 13361 | AC33: 7383.58 | AD33: 300 | AE33: 300 | AF33: 300 | AG33: 0 | AH33: Y | AI33: Y | AJ33: Y | AK33: 0 | AL33: 13361 | AM33: 10840.1 | AN33: 2520.9 | AO33: 13361 | AP33: 300 | AQ33: 300 | AR33: 13361 | AS33: 300 | AT33: 2381.8 | AU33: 46069 | AV33: 46072 | AW33: - | AX33: 0 | AY33: 0 | AZ33: HUAWEI | BD33: 3 | BE33: 6 | BF33: COMPLETED | BG33: MBB | BH33: 10840.1 | BI33: 46081 | BJ33: 15 | BK33: 2520.9 | BL33: 46087 | BM33: 21 | BN33: 13361 | BO33: 0 | BP33: =G33&BG33 -> HAEMBB
A34: EP26020006 | B34: HAE-Cap_Q126-PTHAM | C34: PTHAM_2025 Capacity Expansion Ph8_EXP_ER | D34: 9765.38 | E34: 11909 | F34: 46066 | G34: HAE | H34: Cap_Q126 | I34: PTHAM | J34: BOONCHOT BORIWUT | K34: ER | L34: 46065 | M34: 46065 | N34: 46065 | O34: INHOUSE Adirek Kong-ang | P34: - | Q34: INHOUSE | R34: Adisak Chanmao | S34: น.ส. หทัยรัตน์ สิงห์แก้ว | T34: 26WK7 | U34: 793 | V34: 6951 | W34: 2579 | X34: 1586 | Y34: 11909 | Z34: 1452 | AA34: 46076 | AB34: 13361 | AC34: 7383.58 | AD34: 300 | AE34: 300 | AF34: 300 | AG34: 0 | AH34: Y | AI34: Y | AJ34: Y | AK34: 0 | AL34: 14498 | AM34: 11636 | AN34: 2862 | AO34: 14498 | AP34: 300 | AQ34: 300 | AR34: 14498 | AS34: 300 | AT34: 2381.8 | AU34: 46066 | AV34: 46069 | AW34: - | AX34: 0 | AY34: 0 | AZ34: HUAWEI | BD34: 1 | BE34: 4 | BF34: COMPLETED | BG34: MBB | BH34: 11636 | BI34: 46081 | BJ34: 16 | BK34: 2862 | BL34: 46087 | BM34: 22 | BN34: 14498 | BO34: 0 | BP34: =G34&BG34 -> HAEMBB
A35: EP26020010 | B35: HAE-Cap_Q126-MBGAM | C35: MBGAM_2025 Capacity Expansion Ph8_EXP_ER | D35: 9765.38 | E35: 11909 | F35: 46066 | G35: HAE | H35: Cap_Q126 | I35: MBGAM | J35: BOONCHOT BORIWUT | K35: ER | L35: 46064 | M35: 46064 | N35: 46064 | O35: INHOUSE PHET SAITHONG | P35: - | Q35: INHOUSE | R35: Adisak Chanmao | S35: น.ส. หทัยรัตน์ สิงห์แก้ว | T35: 26WK7 | U35: 793 | V35: 6951 | W35: 2579 | X35: 1586 | Y35: 11909 | Z35: 396 | AA35: 46076 | AB35: 12305 | AC35: 7383.58 | AD35: 300 | AE35: 300 | AF35: 300 | AG35: 0 | AH35: Y | AI35: Y | AJ35: Y | AK35: 0 | AL35: 12833 | AM35: 10470.5 | AN35: 2362.5 | AO35: 12833 | AP35: 300 | AQ35: 300 | AR35: 12833 | AS35: 300 | AT35: 2381.8 | AU35: 46069 | AV35: 46072 | AW35: - | AX35: 0 | AY35: 0 | AZ35: HUAWEI | BD35: 5 | BE35: 8 | BF35: COMPLETED | BG35: MBB | BH35: 10470.5 | BI35: 46081 | BJ35: 17 | BK35: 2362.5 | BL35: 46096 | BM35: 32 | BN35: 12833 | BO35: 0 | BP35: =G35&BG35 -> HAEMBB
A36: EP26020015 | B36: HAE-Cap_Q126-HAMHM | C36: HAMHM_2025 Capacity Expansion Ph8_EXP_ER | D36: 13179.04 | E36: 16072 | F36: 46066 | G36: HAE | H36: Cap_Q126 | I36: HAMHM | J36: BOONCHOT BORIWUT | K36: ER | L36: 46067 | M36: 46067 | N36: 46067 | O36: INHOUSE Adirek Kong-ang | P36: - | Q36: INHOUSE | R36: Adisak Chanmao | S36: น.ส. หทัยรัตน์ สิงห์แก้ว | T36: 26WK7 | U36: 793 | V36: 8537 | W36: 2579 | X36: 4163 | Y36: 16072 | Z36: 1452 | AA36: 46076 | AB36: 17524 | AC36: 9964.64 | AD36: 300 | AE36: 300 | AF36: 300 | AG36: 0 | AH36: Y | AI36: Y | AJ36: Y | AK36: 0 | AL36: 16996 | AM36: 14157.7 | AN36: 2838.3 | AO36: 16996 | AP36: 540 | AQ36: 60 | AR36: 16996 | AS36: 60 | AT36: 3214.4 | AU36: 46068 | AV36: 46070 | AW36: - | AX36: 0 | AY36: 240 | AZ36: HUAWEI | BD36: 1 | BE36: 3 | BF36: COMPLETED | BG36: MBB | BH36: 14157.7 | BI36: 46081 | BJ36: 14 | BK36: 2838.3 | BL36: 46087 | BM36: 20 | BN36: 16996 | BO36: 528 | BP36: =G36&BG36 -> HAEMBB
A37: EP26020019 | B37: HAE-Cap_Q126-CWKWM | C37: CWKWM_2025 Capacity Expansion Ph8_EXP_ER | D37: 14111.38 | E37: 17209 | F37: 46066 | G37: HAE | H37: Cap_Q126 | I37: CWKWM | J37: BOONCHOT BORIWUT | K37: ER | L37: 46063 | M37: 46063 | N37: 46063 | O37: นาย อภิชาติ ฟังสันเทียะ | P37: VD00235 | Q37: SUBCON | R37: Adisak Chanmao | S37: น.ส. หทัยรัตน์ สิงห์แก้ว | T37: 26WK7 | U37: 793 | V37: 9674 | W37: 2579 | X37: 4163 | Y37: 17209 | Z37: 1056 | AA37: 46076 | AB37: 18265 | AC37: 10669.58 | AD37: 7840 | AE37: 7540 | AF37: 300 | AG37: 0 | AH37: Y | AI37: Y | AJ37: Y | AK37: 0 | AL37: 18926 | AM37: 15508.7 | AN37: 3417.3 | AO37: 18926 | AP37: 7900 | AQ37: 7780 | AR37: 18926 | AS37: 7780 | AT37: 0 | AU37: 46064 | AV37: 46068 | AW37: - | AX37: 0 | AY37: 60 | AZ37: HUAWEI | BD37: 1 | BE37: 5 | BF37: COMPLETED | BG37: MBB | BH37: 15508.7 | BI37: 46081 | BJ37: 18 | BK37: 3417.3 | BL37: 46087 | BM37: 24 | BN37: 18926 | BO37: 0 | BP37: =G37&BG37 -> HAEMBB
A38: EP26020029 | B38: TME-DIS_ATN-CBR0549 | C38: CBR0549-AC-02_D_Dismantle_EAST_R3 | D38: 1687.29 | E38: 2081 | F38: 46066 | G38: TME | H38: DIS_ATN | I38: CBR0549 | J38: BOONCHOT BORIWUT | K38: ER | L38: 46064 | M38: 46064 | N38: 46064 | O38: บริษัท สุพรรณ เทเลคอม จำกัด | P38: VD00327 | Q38: SUBCON | R38: Adisak Chanmao | S38: Sermsiri Bampentam | T38: 26WK7 | U38: 0 | V38: 1970 | W38: 0 | X38: 111 | Y38: 2081 | Z38: 0 | AA38: - | AB38: 2081 | AC38: 1500 | AD38: 1230 | AE38: 1230 | AF38: 0 | AG38: 0 | AH38: Y | AI38: Y | AJ38: Y | AK38: 0 | AL38: 2081 | AM38: 1687 | AN38: 394 | AO38: 2081 | AP38: 1230 | AQ38: 1230 | AR38: 2081 | AS38: 1230 | AT38: 0 | AU38: 46064 | AV38: 46076 | AW38: - | AX38: 0 | AY38: 0 | AZ38: HUAWEI | BD38: 0 | BE38: 12 | BF38: COMPLETED | BG38: IPRAN | BH38: 1687 | BI38: 46081 | BJ38: 17 | BK38: 394 | BL38: 46115 | BM38: 51 | BN38: 2081 | BO38: 0 | BP38: =G38&BG38 -> TMEIPRAN
A39: EP26020030 | B39: TME-DIS_ATN-CCO0015 | C39: CCO0015-AC-01_D_Dismantle_EAST_R3 | D39: 1687.29 | E39: 2081 | F39: 46066 | G39: TME | H39: DIS_ATN | I39: CCO0015 | J39: BOONCHOT BORIWUT | K39: ER | L39: 46063 | M39: 46063 | N39: 46063 | O39: นาย ชัชวาล เคราะห์ดี | P39: VD01205 | Q39: SUBCON | R39: Adisak Chanmao | S39: Sermsiri Bampentam | T39: 26WK7 | U39: 0 | V39: 1970 | W39: 0 | X39: 111 | Y39: 2081 | Z39: 0 | AA39: - | AB39: 2081 | AC39: 1500 | AD39: 1230 | AE39: 1230 | AF39: 0 | AG39: 0 | AH39: Y | AI39: Y | AJ39: Y | AK39: 0 | AL39: 2081 | AM39: 1687 | AN39: 0 | AO39: 1687 | AP39: 1230 | AQ39: 1230 | AR39: 1687 | AS39: 1230 | AT39: 0 | AU39: 46063 | AV39: 46076 | AW39: - | AX39: 394 | AY39: 0 | AZ39: HUAWEI | BD39: 0 | BE39: 13 | BF39: COMPLETED | BG39: IPRAN | BH39: 1687 | BI39: 46081 | BJ39: 18 | BK39: 394 | BL39: 46230 | BM39: 167 | BN39: 2081 | BO39: 0 | BP39: =G39&BG39 -> TMEIPRAN
A40: EP26020031 | B40: TME-DIS_ATN-CBI0073 | C40: CBI0073-AC-01_D_Dismantle_EAST_R3 | D40: 1687.29 | E40: 2081 | F40: 46066 | G40: TME | H40: DIS_ATN | I40: CBI0073 | J40: BOONCHOT BORIWUT | K40: ER | L40: 46065 | M40: 46065 | N40: 46065 | O40: นาย ชัชวาล เคราะห์ดี | P40: VD01205 | Q40: SUBCON | R40: Adisak Chanmao | S40: Sermsiri Bampentam | T40: 26WK7 | U40: 0 | V40: 1970 | W40: 0 | X40: 111 | Y40: 2081 | Z40: 0 | AA40: - | AB40: 2081 | AC40: 1500 | AD40: 1230 | AE40: 1230 | AF40: 0 | AG40: 0 | AH40: Y | AI40: Y | AJ40: Y | AK40: 0 | AL40: 2081 | AM40: 1687 | AN40: 394 | AO40: 2081 | AP40: 1230 | AQ40: 1230 | AR40: 2081 | AS40: 1230 | AT40: 0 | AU40: 46065 | AV40: 46076 | AW40: - | AX40: 0 | AY40: 0 | AZ40: HUAWEI | BD40: 0 | BE40: 11 | BF40: COMPLETED | BG40: IPRAN | BH40: 1687 | BI40: 46081 | BJ40: 16 | BK40: 394 | BL40: 46115 | BM40: 50 | BN40: 2081 | BO40: 0 | BP40: =G40&BG40 -> TMEIPRAN
A41: EP26020032 | B41: TME-DIS_ATN-CCO0016 | C41: CCO0016-AC-01_D_Dismantle_EAST_R3 | D41: 1687.29 | E41: 2081 | F41: 46066 | G41: TME | H41: DIS_ATN | I41: CCO0016 | J41: BOONCHOT BORIWUT | K41: ER | L41: 46063 | M41: 46063 | N41: 46063 | O41: นาย ชัชวาล เคราะห์ดี | P41: VD01205 | Q41: SUBCON | R41: Adisak Chanmao | S41: Sermsiri Bampentam | T41: 26WK7 | U41: 0 | V41: 1970 | W41: 0 | X41: 111 | Y41: 2081 | Z41: 0 | AA41: - | AB41: 2081 | AC41: 1500 | AD41: 1230 | AE41: 1230 | AF41: 0 | AG41: 0 | AH41: Y | AI41: Y | AJ41: Y | AK41: 0 | AL41: 2081 | AM41: 1687 | AN41: 0 | AO41: 1687 | AP41: 1230 | AQ41: 1230 | AR41: 1687 | AS41: 1230 | AT41: 0 | AU41: 46063 | AV41: 46076 | AW41: - | AX41: 394 | AY41: 0 | AZ41: HUAWEI | BD41: 0 | BE41: 13 | BF41: COMPLETED | BG41: IPRAN | BH41: 1687 | BI41: 46081 | BJ41: 18 | BK41: 394 | BL41: 46230 | BM41: 167 | BN41: 2081 | BO41: 0 | BP41: =G41&BG41 -> TMEIPRAN
A42: EP26020033 | B42: TME-DIS_ATN-CCO0135 | C42: CCO0135-AC-01_D_Dismantle_EAST_R3 | D42: 1687.29 | E42: 2081 | F42: 46066 | G42: TME | H42: DIS_ATN | I42: CCO0135 | J42: BOONCHOT BORIWUT | K42: ER | L42: 46064 | M42: 46064 | N42: 46064 | O42: นาย ชัชวาล เคราะห์ดี | P42: VD01205 | Q42: SUBCON | R42: Adisak Chanmao | S42: Sermsiri Bampentam | T42: 26WK7 | U42: 0 | V42: 1970 | W42: 0 | X42: 111 | Y42: 2081 | Z42: 0 | AA42: - | AB42: 2081 | AC42: 1500 | AD42: 1230 | AE42: 1230 | AF42: 0 | AG42: 0 | AH42: Y | AI42: Y | AJ42: Y | AK42: 0 | AL42: 2081 | AM42: 1687 | AN42: 0 | AO42: 1687 | AP42: 1230 | AQ42: 1230 | AR42: 1687 | AS42: 1230 | AT42: 0 | AU42: 46064 | AV42: 46076 | AW42: - | AX42: 394 | AY42: 0 | AZ42: HUAWEI | BD42: 0 | BE42: 12 | BF42: COMPLETED | BG42: IPRAN | BH42: 1687 | BI42: 46081 | BJ42: 17 | BK42: 394 | BL42: 46230 | BM42: 166 | BN42: 2081 | BO42: 0 | BP42: =G42&BG42 -> TMEIPRAN
A43: EP26020035 | B43: TME-DIS_ATN-CBR0034 | C43: CBR0034-AC-01_D_Dismantle_EAST_R3 | D43: 1687.29 | E43: 2081 | F43: 46066 | G43: TME | H43: DIS_ATN | I43: CBR0034 | J43: BOONCHOT BORIWUT | K43: ER | L43: 46064 | M43: 46064 | N43: 46064 | O43: บริษัท สุพรรณ เทเลคอม จำกัด | P43: VD00327 | Q43: SUBCON | R43: Adisak Chanmao | S43: Sermsiri Bampentam | T43: 26WK7 | U43: 0 | V43: 1970 | W43: 0 | X43: 111 | Y43: 2081 | Z43: 0 | AA43: - | AB43: 2081 | AC43: 1500 | AD43: 1230 | AE43: 1230 | AF43: 0 | AG43: 0 | AH43: Y | AI43: Y | AJ43: Y | AK43: 0 | AL43: 2081 | AM43: 1687 | AN43: 394 | AO43: 2081 | AP43: 1230 | AQ43: 1230 | AR43: 2081 | AS43: 1230 | AT43: 0 | AU43: 46064 | AV43: 46076 | AW43: - | AX43: 0 | AY43: 0 | AZ43: HUAWEI | BD43: 0 | BE43: 12 | BF43: COMPLETED | BG43: IPRAN | BH43: 1687 | BI43: 46081 | BJ43: 17 | BK43: 394 | BL43: 46115 | BM43: 51 | BN43: 2081 | BO43: 0 | BP43: =G43&BG43 -> TMEIPRAN
A44: EP26020036 | B44: TME-DIS_ATN-CBI0137 | C44: CBI0137-AC-02_D_Dismantle_EAST_R3 | D44: 1687.29 | E44: 2081 | F44: 46066 | G44: TME | H44: DIS_ATN | I44: CBI0137 | J44: BOONCHOT BORIWUT | K44: ER | L44: 46065 | M44: 46065 | N44: 46065 | O44: บริษัท สุพรรณ เทเลคอม จำกัด | P44: VD00327 | Q44: SUBCON | R44: Adisak Chanmao | S44: Sermsiri Bampentam | T44: 26WK7 | U44: 0 | V44: 1970 | W44: 0 | X44: 111 | Y44: 2081 | Z44: 0 | AA44: - | AB44: 2081 | AC44: 1500 | AD44: 1230 | AE44: 1230 | AF44: 0 | AG44: 0 | AH44: Y | AI44: Y | AJ44: Y | AK44: 0 | AL44: 2081 | AM44: 1687 | AN44: 394 | AO44: 2081 | AP44: 1230 | AQ44: 1230 | AR44: 2081 | AS44: 1230 | AT44: 0 | AU44: 46065 | AV44: 46076 | AW44: - | AX44: 0 | AY44: 0 | AZ44: HUAWEI | BD44: 0 | BE44: 11 | BF44: COMPLETED | BG44: IPRAN | BH44: 1687 | BI44: 46081 | BJ44: 16 | BK44: 394 | BL44: 46115 | BM44: 50 | BN44: 2081 | BO44: 0 | BP44: =G44&BG44 -> TMEIPRAN
A45: EP26020057 | B45: HAE-NEWSITE-CPWHM | C45: CPWHM_2024 Coverage Expansion ph.2_New Site-Relocate_ER | D45: 40268.56 | E45: 49108 | F45: 46066 | G45: HAE | H45: NEWSITE | I45: CPWHM | J45: BOONCHOT BORIWUT | K45: ER | L45: 46065 | M45: 46069 | N45: 46069 | O45: นาย อภิชาติ ฟังสันเทียะ | P45: VD00235 | Q45: SUBCON | R45: Adisak Chanmao | S45: น.ส. หทัยรัตน์ สิงห์แก้ว | T45: 26WK8 | U45: 793 | V45: 38992 | W45: 7737 | X45: 1586 | Y45: 49108 | Z45: 0 | AA45: - | AB45: 49108 | AC45: 30446.96 | AD45: 21695 | AE45: 21395 | AF45: 300 | AG45: 0 | AH45: Y | AI45: Y | AJ45: Y | AK45: 0 | AL45: 49108 | AM45: 37410.4 | AN45: 11697.6 | AO45: 49108 | AP45: 21695 | AQ45: 21695 | AR45: 49108 | AS45: 21695 | AT45: 0 | AU45: 46071 | AV45: 46073 | AW45: - | AX45: 0 | AY45: 0 | AZ45: HUAWEI | BD45: 2 | BE45: 4 | BF45: COMPLETED | BG45: MBB | BH45: 37410.4 | BI45: 46073 | BJ45: 4 | BK45: 11697.6 | BL45: 46101 | BM45: 32 | BN45: 49108 | BO45: 0 | BP45: =G45&BG45 -> HAEMBB
A46: EP26020007 | B46: HAE-Cap_Q126-RMBTM | C46: RMBTM_2025 Capacity Expansion Ph8_EXP_ER | D46: 14935.48 | E46: 18214 | F46: 46066 | G46: HAE | H46: Cap_Q126 | I46: RMBTM | J46: BOONCHOT BORIWUT | K46: ER | L46: 46071 | M46: 46072 | N46: 46072 | O46: INHOUSE WACHIRA SAOWARO | P46: - | Q46: INHOUSE | R46: Adisak Chanmao | S46: น.ส. หทัยรัตน์ สิงห์แก้ว | T46: 26WK8 | U46: 793 | V46: 10679 | W46: 2579 | X46: 4163 | Y46: 18214 | Z46: 0 | AA46: - | AB46: 18214 | AC46: 11292.68 | AD46: 300 | AE46: 600 | AF46: 300 | AG46: 0 | AH46: Y | AI46: Y | AJ46: Y | AK46: 0 | AL46: 18214 | AM46: 15010.3 | AN46: 3203.7 | AO46: 18214 | AP46: 300 | AQ46: 300 | AR46: 18214 | AS46: 240 | AT46: 3642.8 | AU46: 46072 | AV46: 46083 | AW46: - | AX46: 0 | AY46: 60 | AZ46: HUAWEI | BD46: 0 | BE46: 11 | BF46: COMPLETED | BG46: MBB | BH46: 15010.3 | BI46: 46081 | BJ46: 9 | BK46: 3203.7 | BL46: 46087 | BM46: 15 | BN46: 18214 | BO46: 0 | BP46: =G46&BG46 -> HAEMBB
A47: EP26020008 | B47: HAE-Cap_Q126-MECPM | C47: MECPM_2025 Capacity Expansion Ph8_EXP_ER | D47: 9765.38 | E47: 11909 | F47: 46066 | G47: HAE | H47: Cap_Q126 | I47: MECPM | J47: BOONCHOT BORIWUT | K47: ER | L47: 46072 | M47: 46072 | N47: 46072 | O47: INHOUSE PHET SAITHONG | P47: - | Q47: INHOUSE | R47: Adisak Chanmao | S47: น.ส. หทัยรัตน์ สิงห์แก้ว | T47: 26WK8 | U47: 793 | V47: 6951 | W47: 2579 | X47: 1586 | Y47: 11909 | Z47: 264 | AA47: 46076 | AB47: 12173 | AC47: 7383.58 | AD47: 300 | AE47: 300 | AF47: 300 | AG47: 0 | AH47: Y | AI47: Y | AJ47: Y | AK47: 0 | AL47: 12173 | AM47: 10008.5 | AN47: 2164.5 | AO47: 12173 | AP47: 300 | AQ47: 300 | AR47: 12173 | AS47: 240 | AT47: 2381.8 | AU47: 46078 | AV47: 46083 | AW47: - | AX47: 0 | AY47: 60 | AZ47: HUAWEI | BD47: 6 | BE47: 11 | BF47: COMPLETED | BG47: MBB | BH47: 10008.5 | BI47: 46087 | BJ47: 15 | BK47: 2164.5 | BL47: 46101 | BM47: 29 | BN47: 12173 | BO47: 0 | BP47: =G47&BG47 -> HAEMBB
A48: EP26020009 | B48: HAE-Cap_Q126-SBWMM | C48: SBWMM_2025 Capacity Expansion Ph8_EXP_ER | D48: 15802.22 | E48: 19271 | F48: 46066 | G48: HAE | H48: Cap_Q126 | I48: SBWMM | J48: BOONCHOT BORIWUT | K48: ER | L48: 46070 | M48: 46070 | N48: 46070 | O48: INHOUSE PHET SAITHONG | P48: - | Q48: INHOUSE | R48: Adisak Chanmao | S48: น.ส. หทัยรัตน์ สิงห์แก้ว | T48: 26WK8 | U48: 793 | V48: 11736 | W48: 2579 | X48: 4163 | Y48: 19271 | Z48: 0 | AA48: - | AB48: 19271 | AC48: 11948.02 | AD48: 300 | AE48: 600 | AF48: 300 | AG48: 0 | AH48: Y | AI48: Y | AJ48: Y | AK48: 0 | AL48: 19271 | AM48: 15750.2 | AN48: 3520.8 | AO48: 19271 | AP48: 300 | AQ48: 300 | AR48: 19271 | AS48: 240 | AT48: 3854.2 | AU48: 46073 | AV48: 46078 | AW48: - | AX48: 0 | AY48: 60 | AZ48: HUAWEI | BD48: 3 | BE48: 8 | BF48: COMPLETED | BG48: MBB | BH48: 15750.2 | BI48: 46087 | BJ48: 17 | BK48: 3520.8 | BL48: 46087 | BM48: 17 | BN48: 19271 | BO48: 0 | BP48: =G48&BG48 -> HAEMBB
A49: EP26020013 | B49: HAE-Cap_Q126-TPSEM | C49: TPSEM_2025 Capacity Expansion Ph8_EXP_ER | D49: 15369.26 | E49: 18743 | F49: 46066 | G49: HAE | H49: Cap_Q126 | I49: TPSEM | J49: BOONCHOT BORIWUT | K49: ER | L49: 46070 | M49: 46070 | N49: 46070 | O49: INHOUSE WACHIRA SAOWARO | P49: - | Q49: INHOUSE | R49: Adisak Chanmao | S49: น.ส. หทัยรัตน์ สิงห์แก้ว | T49: 26WK8 | U49: 793 | V49: 11208 | W49: 2579 | X49: 4163 | Y49: 18743 | Z49: 0 | AA49: - | AB49: 18743 | AC49: 11620.66 | AD49: 300 | AE49: 600 | AF49: 300 | AG49: 0 | AH49: Y | AI49: Y | AJ49: Y | AK49: 0 | AL49: 18743 | AM49: 15380.6 | AN49: 3362.4 | AO49: 18743 | AP49: 300 | AQ49: 300 | AR49: 18743 | AS49: 240 | AT49: 3748.6 | AU49: 46071 | AV49: 46083 | AW49: - | AX49: 0 | AY49: 60 | AZ49: HUAWEI | BD49: 1 | BE49: 13 | BF49: COMPLETED | BG49: MBB | BH49: 15380.6 | BI49: 46081 | BJ49: 11 | BK49: 3362.4 | BL49: 46101 | BM49: 31 | BN49: 18743 | BO49: 0 | BP49: =G49&BG49 -> HAEMBB
A50: EP26020016 | B50: HAE-Cap_Q126-BOBKM | C50: BOBKM_2025 Capacity Expansion Ph8_EXP_ER | D50: 13352.88 | E50: 16284 | F50: 46066 | G50: HAE | H50: Cap_Q126 | I50: BOBKM | J50: BOONCHOT BORIWUT | K50: ER | L50: 46064 | M50: 46071 | N50: 46071 | O50: นาย อภิชาติ ฟังสันเทียะ | P50: VD00235 | Q50: SUBCON | R50: Adisak Chanmao | S50: น.ส. หทัยรัตน์ สิงห์แก้ว | T50: 26WK8 | U50: 793 | V50: 8749 | W50: 2579 | X50: 4163 | Y50: 16284 | Z50: 1056 | AA50: 46076 | AB50: 17340 | AC50: 10096.08 | AD50: 7390 | AE50: 7090 | AF50: 300 | AG50: 0 | AH50: Y | AI50: Y | AJ50: Y | AK50: 0 | AL50: 17340 | AM50: 14398.5 | AN50: 2941.5 | AO50: 17340 | AP50: 7390 | AQ50: 7390 | AR50: 17340 | AS50: 7330 | AT50: 0 | AU50: 46072 | AV50: 46074 | AW50: - | AX50: 0 | AY50: 60 | AZ50: HUAWEI | BD50: 1 | BE50: 3 | BF50: COMPLETED | BG50: MBB | BH50: 14398.5 | BI50: 46087 | BJ50: 16 | BK50: 2941.5 | BL50: 46087 | BM50: 16 | BN50: 17340 | BO50: 0 | BP50: =G50&BG50 -> HAEMBB
A51: EP26020018 | B51: HAE-Cap_Q126-BTJMM | C51: BTJMM_2025 Capacity Expansion Ph8_EXP_ER | D51: 24149.82 | E51: 29451 | F51: 46066 | G51: HAE | H51: Cap_Q126 | I51: BTJMM | J51: BOONCHOT BORIWUT | K51: ER | L51: 46072 | M51: 46072 | N51: 46072 | O51: INHOUSE WACHIRA SAOWARO | P51: - | Q51: INHOUSE | R51: Adisak Chanmao | S51: น.ส. หทัยรัตน์ สิงห์แก้ว | T51: 26WK8 | U51: 793 | V51: 21916 | W51: 2579 | X51: 4163 | Y51: 29451 | Z51: 0 | AA51: - | AB51: 29451 | AC51: 18259.62 | AD51: 300 | AE51: 300 | AF51: 300 | AG51: 0 | AH51: Y | AI51: Y | AJ51: Y | AK51: 0 | AL51: 29451 | AM51: 22876.2 | AN51: 6574.8 | AO51: 29451 | AP51: 300 | AQ51: 300 | AR51: 29451 | AS51: 240 | AT51: 5890.2 | AU51: 46079 | AV51: 46083 | AW51: - | AX51: 0 | AY51: 60 | AZ51: HUAWEI | BD51: 7 | BE51: 11 | BF51: COMPLETED | BG51: MBB | BH51: 22876.2 | BI51: 46087 | BJ51: 15 | BK51: 6574.8 | BL51: 46101 | BM51: 29 | BN51: 29451 | BO51: 0 | BP51: =G51&BG51 -> HAEMBB
A52: EP26020027 | B52: TME-DIS_ATN-CBR0715 | C52: CBR0715-AC-02_D_Dismantle_EAST_R3 | D52: 1687.29 | E52: 2081 | F52: 46066 | G52: TME | H52: DIS_ATN | I52: CBR0715 | J52: BOONCHOT BORIWUT | K52: ER | L52: 46069 | M52: 46069 | N52: 46069 | O52: บริษัท สุพรรณ เทเลคอม จำกัด | P52: VD00327 | Q52: SUBCON | R52: Adisak Chanmao | S52: Sermsiri Bampentam | T52: 26WK8 | U52: 0 | V52: 1970 | W52: 0 | X52: 111 | Y52: 2081 | Z52: 0 | AA52: - | AB52: 2081 | AC52: 1500 | AD52: 1230 | AE52: 1230 | AF52: 0 | AG52: 0 | AH52: Y | AI52: Y | AJ52: Y | AK52: 0 | AL52: 2081 | AM52: 1687 | AN52: 394 | AO52: 2081 | AP52: 1230 | AQ52: 1230 | AR52: 2081 | AS52: 1230 | AT52: 0 | AU52: 46069 | AV52: 46076 | AW52: - | AX52: 0 | AY52: 0 | AZ52: HUAWEI | BD52: 0 | BE52: 7 | BF52: COMPLETED | BG52: IPRAN | BH52: 1687 | BI52: 46081 | BJ52: 12 | BK52: 394 | BL52: 46115 | BM52: 46 | BN52: 2081 | BO52: 0 | BP52: =G52&BG52 -> TMEIPRAN
A53: EP26020028 | B53: TME-DIS_ATN-CBI0357 | C53: CBI0357-AC-02_D_Dismantle_EAST_R3 | D53: 1687.29 | E53: 2081 | F53: 46066 | G53: TME | H53: DIS_ATN | I53: CBI0357 | J53: BOONCHOT BORIWUT | K53: ER | L53: 46069 | M53: 46069 | N53: 46069 | O53: บริษัท สุพรรณ เทเลคอม จำกัด | P53: VD00327 | Q53: SUBCON | R53: Adisak Chanmao | S53: Sermsiri Bampentam | T53: 26WK8 | U53: 0 | V53: 1970 | W53: 0 | X53: 111 | Y53: 2081 | Z53: 0 | AA53: - | AB53: 2081 | AC53: 1500 | AD53: 1230 | AE53: 1230 | AF53: 0 | AG53: 0 | AH53: Y | AI53: Y | AJ53: Y | AK53: 0 | AL53: 2081 | AM53: 1687 | AN53: 394 | AO53: 2081 | AP53: 1230 | AQ53: 1230 | AR53: 2081 | AS53: 1230 | AT53: 0 | AU53: 46069 | AV53: 46076 | AW53: - | AX53: 0 | AY53: 0 | AZ53: HUAWEI | BD53: 0 | BE53: 7 | BF53: COMPLETED | BG53: IPRAN | BH53: 1687 | BI53: 46081 | BJ53: 12 | BK53: 394 | BL53: 46115 | BM53: 46 | BN53: 2081 | BO53: 0 | BP53: =G53&BG53 -> TMEIPRAN
A54: EP26020082 | B54: TME-REPIPRAN-TRT0001 | C54: TRT0001_D_AGG_Exp_EAST_R3 | D54: 3417.82 | E54: 4413 | F54: 46066 | G54: TME | H54: REPIPRAN | I54: TRT0001 | J54: BOONCHOT BORIWUT | K54: ER | L54: 46069 | M54: 46069 | N54: 46069 | O54: บริษัท สุพรรณ เทเลคอม จำกัด | P54: VD00327 | Q54: SUBCON | R54: Adisak Chanmao | S54: Sermsiri Bampentam | T54: 26WK8 | U54: 0 | V54: 4413 | W54: 0 | X54: 0 | Y54: 4413 | Z54: 0 | AA54: - | AB54: 4413 | AC54: 2800 | AD54: 2800 | AE54: 2800 | AF54: 0 | AG54: 0 | AH54: Y | AI54: Y | AJ54: Y | AK54: 0 | AL54: 4413 | AM54: 3530.4 | AN54: 0 | AO54: 3530.4 | AP54: 0 | AQ54: 2800 | AR54: 3530.4 | AS54: 2800 | AT54: 0 | AU54: 46070 | AV54: 46073 | AW54: - | AX54: 882.6 | AY54: 0 | AZ54: HUAWEI | BD54: 1 | BE54: 4 | BF54: COMPLETED | BG54: IPRAN | BH54: 3530.4 | BI54: 46081 | BJ54: 12 | BK54: 882.6 | BL54: 46230 | BM54: 161 | BN54: 4413 | BO54: 0 | BP54: =G54&BG54 -> TMEIPRAN
A55: EP26020073 | B55: TME-DIS_ATN-RYG0021 | C55: RYG0021-AC-01_D_Dismantle_EAST_R3 | D55: 1687.29 | E55: 2081 | F55: 46066 | G55: TME | H55: DIS_ATN | I55: RYG0021 | J55: BOONCHOT BORIWUT | K55: ER | L55: 46070 | M55: 46070 | N55: 46070 | O55: บริษัท สุพรรณ เทเลคอม จำกัด | P55: VD00327 | Q55: SUBCON | R55: Adisak Chanmao | S55: Sermsiri Bampentam | T55: 26WK8 | U55: 0 | V55: 1970 | W55: 0 | X55: 111 | Y55: 2081 | Z55: 0 | AA55: - | AB55: 2081 | AC55: 1500 | AD55: 1230 | AE55: 1230 | AF55: 0 | AG55: 0 | AH55: Y | AI55: Y | AJ55: Y | AK55: 0 | AL55: 2081 | AM55: 1687 | AN55: 0 | AO55: 1687 | AP55: 1230 | AQ55: 1230 | AR55: 1687 | AS55: 1230 | AT55: 0 | AU55: 46070 | AV55: 46078 | AW55: - | AX55: 394 | AY55: 0 | AZ55: HUAWEI | BD55: 0 | BE55: 8 | BF55: COMPLETED | BG55: IPRAN | BH55: 1687 | BI55: 46081 | BJ55: 11 | BK55: 394 | BL55: 46230 | BM55: 160 | BN55: 2081 | BO55: 0 | BP55: =G55&BG55 -> TMEIPRAN
A56: EP26020074 | B56: TME-DIS_ATN-RYG0303 | C56: RYG0303-AC-02_D_Dismantle_EAST_R3 | D56: 1687.29 | E56: 2081 | F56: 46066 | G56: TME | H56: DIS_ATN | I56: RYG0303 | J56: BOONCHOT BORIWUT | K56: ER | L56: 46070 | M56: 46070 | N56: 46070 | O56: บริษัท สุพรรณ เทเลคอม จำกัด | P56: VD00327 | Q56: SUBCON | R56: Adisak Chanmao | S56: Sermsiri Bampentam | T56: 26WK8 | U56: 0 | V56: 1970 | W56: 0 | X56: 111 | Y56: 2081 | Z56: 0 | AA56: - | AB56: 2081 | AC56: 1500 | AD56: 1230 | AE56: 1230 | AF56: 0 | AG56: 0 | AH56: Y | AI56: Y | AJ56: Y | AK56: 0 | AL56: 2081 | AM56: 1687 | AN56: 0 | AO56: 1687 | AP56: 1230 | AQ56: 1230 | AR56: 1687 | AS56: 1230 | AT56: 0 | AU56: 46070 | AV56: 46078 | AW56: - | AX56: 394 | AY56: 0 | AZ56: HUAWEI | BD56: 0 | BE56: 8 | BF56: COMPLETED | BG56: IPRAN | BH56: 1687 | BI56: 46081 | BJ56: 11 | BK56: 394 | BL56: 46230 | BM56: 160 | BN56: 2081 | BO56: 0 | BP56: =G56&BG56 -> TMEIPRAN
A57: EP26020063 | B57: TME-DIS_ATN-RYG0307 | C57: RYG0307-AC-02_D_Dismantle_EAST_R3 | D57: 1687.29 | E57: 2081 | F57: 46066 | G57: TME | H57: DIS_ATN | I57: RYG0307 | J57: BOONCHOT BORIWUT | K57: ER | L57: 46070 | M57: 46070 | N57: 46070 | O57: บริษัท สุพรรณ เทเลคอม จำกัด | P57: VD00327 | Q57: SUBCON | R57: Adisak Chanmao | S57: Sermsiri Bampentam | T57: 26WK8 | U57: 0 | V57: 1970 | W57: 0 | X57: 111 | Y57: 2081 | Z57: 0 | AA57: - | AB57: 2081 | AC57: 1500 | AD57: 1230 | AE57: 1230 | AF57: 0 | AG57: 0 | AH57: Y | AI57: Y | AJ57: Y | AK57: 0 | AL57: 2081 | AM57: 1687 | AN57: 0 | AO57: 1687 | AP57: 1230 | AQ57: 1230 | AR57: 1687 | AS57: 1230 | AT57: 0 | AU57: 46070 | AV57: 46078 | AW57: - | AX57: 394 | AY57: 0 | AZ57: HUAWEI | BD57: 0 | BE57: 8 | BF57: COMPLETED | BG57: IPRAN | BH57: 1687 | BI57: 46081 | BJ57: 11 | BK57: 394 | BL57: 46230 | BM57: 160 | BN57: 2081 | BO57: 0 | BP57: =G57&BG57 -> TMEIPRAN
A58: EP26020067 | B58: TME-DIS_ATN-SKE0009 | C58: SKE0009-AC-01_D_Dismantle_EAST_R3 | D58: 1687.29 | E58: 2081 | F58: 46066 | G58: TME | H58: DIS_ATN | I58: SKE0009 | J58: BOONCHOT BORIWUT | K58: ER | L58: 46070 | M58: 46070 | N58: 46070 | O58: นาย ชัชวาล เคราะห์ดี | P58: VD01205 | Q58: SUBCON | R58: Adisak Chanmao | S58: Sermsiri Bampentam | T58: 26WK8 | U58: 0 | V58: 1970 | W58: 0 | X58: 111 | Y58: 2081 | Z58: 0 | AA58: - | AB58: 2081 | AC58: 1500 | AD58: 1230 | AE58: 1230 | AF58: 0 | AG58: 0 | AH58: Y | AI58: Y | AJ58: Y | AK58: 0 | AL58: 2081 | AM58: 1687 | AN58: 0 | AO58: 1687 | AP58: 1230 | AQ58: 1230 | AR58: 1687 | AS58: 1230 | AT58: 0 | AU58: 46070 | AV58: 46078 | AW58: - | AX58: 394 | AY58: 0 | AZ58: HUAWEI | BD58: 0 | BE58: 8 | BF58: COMPLETED | BG58: IPRAN | BH58: 1687 | BI58: 46081 | BJ58: 11 | BK58: 394 | BL58: 46230 | BM58: 160 | BN58: 2081 | BO58: 0 | BP58: =G58&BG58 -> TMEIPRAN
A59: EP26020072 | B59: TME-DIS_ATN-SKO0094 | C59: SKO0094-AC-01_D_Dismantle_EAST_R3 | D59: 1687.29 | E59: 2081 | F59: 46066 | G59: TME | H59: DIS_ATN | I59: SKO0094 | J59: BOONCHOT BORIWUT | K59: ER | L59: 46070 | M59: 46070 | N59: 46070 | O59: นาย ชัชวาล เคราะห์ดี | P59: VD01205 | Q59: SUBCON | R59: Adisak Chanmao | S59: Sermsiri Bampentam | T59: 26WK8 | U59: 0 | V59: 1970 | W59: 0 | X59: 111 | Y59: 2081 | Z59: 0 | AA59: - | AB59: 2081 | AC59: 1500 | AD59: 1230 | AE59: 1230 | AF59: 0 | AG59: 0 | AH59: Y | AI59: Y | AJ59: Y | AK59: 0 | AL59: 2081 | AM59: 1687 | AN59: 0 | AO59: 1687 | AP59: 1230 | AQ59: 1230 | AR59: 1687 | AS59: 1230 | AT59: 0 | AU59: 46071 | AV59: 46092 | AW59: - | AX59: 394 | AY59: 0 | AZ59: HUAWEI | BD59: 1 | BE59: 22 | BF59: COMPLETED | BG59: IPRAN | BH59: 1687 | BI59: 46087 | BJ59: 17 | BK59: 0 | BN59: 1687 | BO59: 394 | BP59: =G59&BG59 -> TMEIPRAN
A60: EP26020069 | B60: TME-DIS_ATN-CTB0014 | C60: CTB0014-AC-01_D_Dismantle_EAST_R3 | D60: 1687.29 | E60: 2081 | F60: 46066 | G60: TME | H60: DIS_ATN | I60: CTB0014 | J60: BOONCHOT BORIWUT | K60: ER | L60: 46071 | M60: 46071 | N60: 46071 | O60: บริษัท สุพรรณ เทเลคอม จำกัด | P60: VD00327 | Q60: SUBCON | R60: Adisak Chanmao | S60: Sermsiri Bampentam | T60: 26WK8 | U60: 0 | V60: 1970 | W60: 0 | X60: 111 | Y60: 2081 | Z60: 0 | AA60: - | AB60: 2081 | AC60: 1500 | AD60: 1230 | AE60: 1230 | AF60: 0 | AG60: 0 | AH60: Y | AI60: Y | AJ60: Y | AK60: 0 | AL60: 2081 | AM60: 1687 | AN60: 0 | AO60: 1687 | AP60: 1230 | AQ60: 1230 | AR60: 1687 | AS60: 1230 | AT60: 0 | AU60: 46071 | AV60: 46078 | AW60: - | AX60: 394 | AY60: 0 | AZ60: HUAWEI | BD60: 0 | BE60: 7 | BF60: COMPLETED | BG60: IPRAN | BH60: 1687 | BI60: 46081 | BJ60: 10 | BK60: 394 | BL60: 46230 | BM60: 159 | BN60: 2081 | BO60: 0 | BP60: =G60&BG60 -> TMEIPRAN
A61: EP26020070 | B61: TME-DIS_ATN-CTI0012 | C61: CTI0012-AC-01_D_Dismantle_EAST_R3 | D61: 1687.29 | E61: 2081 | F61: 46066 | G61: TME | H61: DIS_ATN | I61: CTI0012 | J61: BOONCHOT BORIWUT | K61: ER | L61: 46071 | M61: 46071 | N61: 46071 | O61: บริษัท สุพรรณ เทเลคอม จำกัด | P61: VD00327 | Q61: SUBCON | R61: Adisak Chanmao | S61: Sermsiri Bampentam | T61: 26WK8 | U61: 0 | V61: 1970 | W61: 0 | X61: 111 | Y61: 2081 | Z61: 0 | AA61: - | AB61: 2081 | AC61: 1500 | AD61: 1230 | AE61: 1230 | AF61: 0 | AG61: 0 | AH61: Y | AI61: Y | AJ61: Y | AK61: 0 | AL61: 2081 | AM61: 1687 | AN61: 0 | AO61: 1687 | AP61: 1230 | AQ61: 1230 | AR61: 1687 | AS61: 1230 | AT61: 0 | AU61: 46071 | AV61: 46078 | AW61: - | AX61: 394 | AY61: 0 | AZ61: HUAWEI | BD61: 0 | BE61: 7 | BF61: COMPLETED | BG61: IPRAN | BH61: 1687 | BI61: 46081 | BJ61: 10 | BK61: 394 | BL61: 46230 | BM61: 159 | BN61: 2081 | BO61: 0 | BP61: =G61&BG61 -> TMEIPRAN
A62: EP26020062 | B62: TME-DIS_ATN-CTI0023 | C62: CTI0023-AC-01_D_Dismantle_EAST_R3 | D62: 1687.29 | E62: 2081 | F62: 46066 | G62: TME | H62: DIS_ATN | I62: CTI0023 | J62: BOONCHOT BORIWUT | K62: ER | L62: 46071 | M62: 46071 | N62: 46071 | O62: บริษัท สุพรรณ เทเลคอม จำกัด | P62: VD00327 | Q62: SUBCON | R62: Adisak Chanmao | S62: Sermsiri Bampentam | T62: 26WK8 | U62: 0 | V62: 1970 | W62: 0 | X62: 111 | Y62: 2081 | Z62: 0 | AA62: - | AB62: 2081 | AC62: 1500 | AD62: 1230 | AE62: 1230 | AF62: 0 | AG62: 0 | AH62: Y | AI62: Y | AJ62: Y | AK62: 0 | AL62: 2081 | AM62: 1687 | AN62: 0 | AO62: 1687 | AP62: 1230 | AQ62: 1230 | AR62: 1687 | AS62: 1230 | AT62: 0 | AU62: 46071 | AV62: 46078 | AW62: - | AX62: 394 | AY62: 0 | AZ62: HUAWEI | BD62: 0 | BE62: 7 | BF62: COMPLETED | BG62: IPRAN | BH62: 1687 | BI62: 46081 | BJ62: 10 | BK62: 394 | BL62: 46230 | BM62: 159 | BN62: 2081 | BO62: 0 | BP62: =G62&BG62 -> TMEIPRAN
A63: EP26020071 | B63: TME-DIS_ATN-NYK0008 | C63: NYK0008-AC-01_D_Dismantle_EAST_R3 | D63: 1687.29 | E63: 2081 | F63: 46066 | G63: TME | H63: DIS_ATN | I63: NYK0008 | J63: BOONCHOT BORIWUT | K63: ER | L63: 46071 | M63: 46071 | N63: 46071 | O63: นาย ชัชวาล เคราะห์ดี | P63: VD01205 | Q63: SUBCON | R63: Adisak Chanmao | S63: Sermsiri Bampentam | T63: 26WK8 | U63: 0 | V63: 1970 | W63: 0 | X63: 111 | Y63: 2081 | Z63: 0 | AA63: - | AB63: 2081 | AC63: 1500 | AD63: 1230 | AE63: 1230 | AF63: 0 | AG63: 0 | AH63: Y | AI63: Y | AJ63: Y | AK63: 0 | AL63: 2081 | AM63: 1687 | AN63: 0 | AO63: 1687 | AP63: 1230 | AQ63: 1230 | AR63: 1687 | AS63: 1230 | AT63: 0 | AU63: 46071 | AV63: 46078 | AW63: - | AX63: 394 | AY63: 0 | AZ63: HUAWEI | BD63: 0 | BE63: 7 | BF63: COMPLETED | BG63: IPRAN | BH63: 1687 | BI63: 46087 | BJ63: 16 | BK63: 0 | BN63: 1687 | BO63: 394 | BP63: =G63&BG63 -> TMEIPRAN
A64: EP26020058 | B64: TME-DIS_ATN-NYK0019 | C64: NYK0019-AC-01_D_Dismantle_EAST_R3 | D64: 1687.29 | E64: 2081 | F64: 46066 | G64: TME | H64: DIS_ATN | I64: NYK0019 | J64: BOONCHOT BORIWUT | K64: ER | L64: 46071 | M64: 46071 | N64: 46071 | O64: นาย ชัชวาล เคราะห์ดี | P64: VD01205 | Q64: SUBCON | R64: Adisak Chanmao | S64: Sermsiri Bampentam | T64: 26WK8 | U64: 0 | V64: 1970 | W64: 0 | X64: 111 | Y64: 2081 | Z64: 0 | AA64: - | AB64: 2081 | AC64: 1500 | AD64: 1230 | AE64: 1230 | AF64: 0 | AG64: 0 | AH64: Y | AI64: Y | AJ64: Y | AK64: 0 | AL64: 2081 | AM64: 1687 | AN64: 0 | AO64: 1687 | AP64: 1230 | AQ64: 1230 | AR64: 1687 | AS64: 1230 | AT64: 0 | AU64: 46071 | AV64: 46078 | AW64: - | AX64: 394 | AY64: 0 | AZ64: HUAWEI | BD64: 0 | BE64: 7 | BF64: COMPLETED | BG64: IPRAN | BH64: 1687 | BI64: 46087 | BJ64: 16 | BK64: 394 | BL64: 46230 | BM64: 159 | BN64: 2081 | BO64: 0 | BP64: =G64&BG64 -> TMEIPRAN
A65: EP26020059 | B65: TME-DIS_ATN-PRI0004 | C65: PRI0004-AC-01_D_Dismantle_EAST_R3 | D65: 1687.29 | E65: 2081 | F65: 46066 | G65: TME | H65: DIS_ATN | I65: PRI0004 | J65: BOONCHOT BORIWUT | K65: ER | L65: 46072 | M65: 46072 | N65: 46072 | O65: นาย ชัชวาล เคราะห์ดี | P65: VD01205 | Q65: SUBCON | R65: Adisak Chanmao | S65: Sermsiri Bampentam | T65: 26WK8 | U65: 0 | V65: 1970 | W65: 0 | X65: 111 | Y65: 2081 | Z65: 0 | AA65: - | AB65: 2081 | AC65: 1500 | AD65: 1230 | AE65: 1230 | AF65: 0 | AG65: 0 | AH65: Y | AI65: Y | AJ65: Y | AK65: 0 | AL65: 2081 | AM65: 1687 | AN65: 0 | AO65: 1687 | AP65: 1230 | AQ65: 1230 | AR65: 1687 | AS65: 1230 | AT65: 0 | AU65: 46072 | AV65: 46086 | AW65: - | AX65: 394 | AY65: 0 | AZ65: HUAWEI | BD65: 0 | BE65: 14 | BF65: COMPLETED | BG65: IPRAN | BH65: 1687 | BI65: 46087 | BJ65: 15 | BK65: 394 | BL65: 46230 | BM65: 158 | BN65: 2081 | BO65: 0 | BP65: =G65&BG65 -> TMEIPRAN
A66: EP26020061 | B66: TME-DIS_ATN-PRI0006 | C66: PRI0006-AC-01_D_Dismantle_EAST_R3 | D66: 1687.29 | E66: 2081 | F66: 46066 | G66: TME | H66: DIS_ATN | I66: PRI0006 | J66: BOONCHOT BORIWUT | K66: ER | L66: 46072 | M66: 46072 | N66: 46072 | O66: นาย ชัชวาล เคราะห์ดี | P66: VD01205 | Q66: SUBCON | R66: Adisak Chanmao | S66: Sermsiri Bampentam | T66: 26WK8 | U66: 0 | V66: 1970 | W66: 0 | X66: 111 | Y66: 2081 | Z66: 0 | AA66: - | AB66: 2081 | AC66: 1500 | AD66: 1230 | AE66: 1230 | AF66: 0 | AG66: 0 | AH66: Y | AI66: Y | AJ66: Y | AK66: 0 | AL66: 2081 | AM66: 1687 | AN66: 0 | AO66: 1687 | AP66: 1230 | AQ66: 1230 | AR66: 1687 | AS66: 1230 | AT66: 0 | AU66: 46072 | AV66: 46086 | AW66: - | AX66: 394 | AY66: 0 | AZ66: HUAWEI | BD66: 0 | BE66: 14 | BF66: COMPLETED | BG66: IPRAN | BH66: 1687 | BI66: 46087 | BJ66: 15 | BK66: 394 | BL66: 46230 | BM66: 158 | BN66: 2081 | BO66: 0 | BP66: =G66&BG66 -> TMEIPRAN
A67: EP26020064 | B67: TME-DIS_ATN-TRT0120 | C67: TRT0120-AC-02_D_Dismantle_EAST_R3 | D67: 1687.29 | E67: 2081 | F67: 46066 | G67: TME | H67: DIS_ATN | I67: TRT0120 | J67: BOONCHOT BORIWUT | K67: ER | L67: 46072 | M67: 46072 | N67: 46072 | O67: บริษัท สุพรรณ เทเลคอม จำกัด | P67: VD00327 | Q67: SUBCON | R67: Adisak Chanmao | S67: Sermsiri Bampentam | T67: 26WK8 | U67: 0 | V67: 1970 | W67: 0 | X67: 111 | Y67: 2081 | Z67: 0 | AA67: - | AB67: 2081 | AC67: 1500 | AD67: 1230 | AE67: 1230 | AF67: 0 | AG67: 0 | AH67: Y | AI67: Y | AJ67: Y | AK67: 0 | AL67: 2081 | AM67: 1687 | AN67: 0 | AO67: 1687 | AP67: 1230 | AQ67: 1230 | AR67: 1687 | AS67: 1230 | AT67: 0 | AU67: 46072 | AV67: 46086 | AW67: - | AX67: 394 | AY67: 0 | AZ67: HUAWEI | BD67: 0 | BE67: 14 | BF67: COMPLETED | BG67: IPRAN | BH67: 1687 | BI67: 46087 | BJ67: 15 | BK67: 0 | BN67: 1687 | BO67: 394 | BP67: =G67&BG67 -> TMEIPRAN
A68: EP26020066 | B68: TME-DIS_ATN-TRT0006 | C68: TRT0006-AC-01_D_Dismantle_EAST_R3 | D68: 1687.29 | E68: 2081 | F68: 46066 | G68: TME | H68: DIS_ATN | I68: TRT0006 | J68: BOONCHOT BORIWUT | K68: ER | L68: 46073 | M68: 46073 | N68: 46073 | O68: บริษัท สุพรรณ เทเลคอม จำกัด | P68: VD00327 | Q68: SUBCON | R68: Adisak Chanmao | S68: Sermsiri Bampentam | T68: 26WK8 | U68: 0 | V68: 1970 | W68: 0 | X68: 111 | Y68: 2081 | Z68: 0 | AA68: - | AB68: 2081 | AC68: 1500 | AD68: 1230 | AE68: 1230 | AF68: 0 | AG68: 0 | AH68: Y | AI68: Y | AJ68: Y | AK68: 0 | AL68: 2081 | AM68: 1687 | AN68: 0 | AO68: 1687 | AP68: 1230 | AQ68: 1230 | AR68: 1687 | AS68: 1230 | AT68: 0 | AU68: 46073 | AV68: 46092 | AW68: - | AX68: 394 | AY68: 0 | AZ68: HUAWEI | BD68: 0 | BE68: 19 | BF68: COMPLETED | BG68: IPRAN | BH68: 1687 | BI68: 46087 | BJ68: 14 | BK68: 0 | BN68: 1687 | BO68: 394 | BP68: =G68&BG68 -> TMEIPRAN
A69: EP26020068 | B69: TME-DIS_ATN-TRT0165 | C69: TRT0165-AC-02_D_Dismantle_EAST_R3 | D69: 1687.29 | E69: 2081 | F69: 46066 | G69: TME | H69: DIS_ATN | I69: TRT0165 | J69: BOONCHOT BORIWUT | K69: ER | L69: 46073 | M69: 46073 | N69: 46073 | O69: บริษัท สุพรรณ เทเลคอม จำกัด | P69: VD00327 | Q69: SUBCON | R69: Adisak Chanmao | S69: Sermsiri Bampentam | T69: 26WK8 | U69: 0 | V69: 1970 | W69: 0 | X69: 111 | Y69: 2081 | Z69: 0 | AA69: - | AB69: 2081 | AC69: 1500 | AD69: 1230 | AE69: 1230 | AF69: 0 | AG69: 0 | AH69: Y | AI69: Y | AJ69: Y | AK69: 0 | AL69: 2081 | AM69: 1687 | AN69: 0 | AO69: 1687 | AP69: 1230 | AQ69: 1230 | AR69: 1687 | AS69: 1230 | AT69: 0 | AU69: 46073 | AV69: 46086 | AW69: - | AX69: 394 | AY69: 0 | AZ69: HUAWEI | BD69: 0 | BE69: 13 | BF69: COMPLETED | BG69: IPRAN | BH69: 1687 | BI69: 46087 | BJ69: 14 | BK69: 0 | BN69: 1687 | BO69: 394 | BP69: =G69&BG69 -> TMEIPRAN
A70: EP26020075 | B70: HAE-Cap_Q126-NWKYM | C70: NWKYM_2025 Capacity Expansion Ph8_EXP_ER | D70: 10415.64 | E70: 12702 | F70: 46066 | G70: HAE | H70: Cap_Q126 | I70: NWKYM | J70: BOONCHOT BORIWUT | K70: ER | L70: 46076 | M70: 46076 | N70: 46076 | O70: INHOUSE PHET SAITHONG | P70: - | Q70: INHOUSE | R70: Adisak Chanmao | S70: น.ส. หทัยรัตน์ สิงห์แก้ว | T70: 26WK9 | U70: 793 | V70: 10323 | W70: 0 | X70: 1586 | Y70: 12702 | Z70: 0 | AA70: - | AB70: 12702 | AC70: 7875.24 | AD70: 300 | AE70: 300 | AF70: 300 | AG70: 0 | AH70: Y | AI70: Y | AJ70: Y | AK70: 0 | AL70: 13759 | AM70: 11118.7 | AN70: 2640.3 | AO70: 13759 | AP70: 300 | AQ70: 300 | AR70: 13759 | AS70: 300 | AT70: 2540.4 | AU70: 46076 | AV70: 46083 | AW70: - | AX70: 0 | AY70: 0 | AZ70: HUAWEI | BD70: 0 | BE70: 7 | BF70: COMPLETED | BG70: MBB | BH70: 11118.7 | BI70: 46087 | BJ70: 11 | BK70: 2640.3 | BL70: 46101 | BM70: 25 | BN70: 13759 | BO70: 0 | BP70: =G70&BG70 -> HAEMBB
A71: EP26020076 | B71: HAE-Cap_Q126-NREKM | C71: NREKM_2025 Capacity Expansion Ph8_EXP_ER | D71: 9765.38 | E71: 11909 | F71: 46066 | G71: HAE | H71: Cap_Q126 | I71: NREKM | J71: BOONCHOT BORIWUT | K71: ER | L71: 46076 | M71: 46076 | N71: 46076 | O71: นาย อภิชาติ ฟังสันเทียะ | P71: VD00235 | Q71: SUBCON | R71: Adisak Chanmao | S71: น.ส. หทัยรัตน์ สิงห์แก้ว | T71: 26WK9 | U71: 793 | V71: 9530 | W71: 0 | X71: 1586 | Y71: 11909 | Z71: 1056 | AA71: - | AB71: 12965 | AC71: 7383.58 | AD71: 6570 | AE71: 6270 | AF71: 300 | AG71: 0 | AH71: Y | AI71: Y | AJ71: Y | AK71: 0 | AL71: 12965 | AM71: 10562.9 | AN71: 2402.1 | AO71: 12965 | AP71: 6570 | AQ71: 6570 | AR71: 12965 | AS71: 6570 | AT71: 0 | AU71: 46077 | AV71: 46079 | AW71: - | AX71: 0 | AY71: 0 | AZ71: HUAWEI | BD71: 1 | BE71: 3 | BF71: COMPLETED | BG71: MBB | BH71: 10562.9 | BI71: 46087 | BJ71: 11 | BK71: 2402.1 | BL71: 46096 | BM71: 20 | BN71: 12965 | BO71: 0 | BP71: =G71&BG71 -> HAEMBB
A72: EP26020078 | B72: HAE-Cap_Q126-WNUKM | C72: WNUKM_2025 Capacity Expansion Ph8_EXP_ER | D72: 9765.38 | E72: 11909 | F72: 46066 | G72: HAE | H72: Cap_Q126 | I72: WNUKM | J72: BOONCHOT BORIWUT | K72: ER | L72: 46076 | M72: 46077 | N72: 46077 | O72: INHOUSE PHET SAITHONG | P72: - | Q72: INHOUSE | R72: Adisak Chanmao | S72: น.ส. หทัยรัตน์ สิงห์แก้ว | T72: 26WK9 | U72: 793 | V72: 9530 | W72: 0 | X72: 1586 | Y72: 11909 | Z72: 0 | AA72: - | AB72: 11909 | AC72: 7383.58 | AD72: 300 | AE72: 300 | AF72: 300 | AG72: 0 | AH72: Y | AI72: Y | AJ72: Y | AK72: 0 | AL72: 12965 | AM72: 10562.9 | AN72: 2402.1 | AO72: 12965 | AP72: 300 | AQ72: 300 | AR72: 12965 | AS72: 300 | AT72: 2381.8 | AU72: 46078 | AV72: 46079 | AW72: - | AX72: 0 | AY72: 0 | AZ72: HUAWEI | BD72: 1 | BE72: 2 | BF72: COMPLETED | BG72: MBB | BH72: 10562.9 | BI72: 46087 | BJ72: 10 | BK72: 2402.1 | BL72: 46096 | BM72: 19 | BN72: 12965 | BO72: 0 | BP72: =G72&BG72 -> HAEMBB
A73: EP26020083 | B73: TME-DIS_ATN-CCO0017 | C73: CCO0017-AC-01_D_Dismantle_EAST_R3 | D73: 1687.29 | E73: 2081 | F73: 46066 | G73: TME | H73: DIS_ATN | I73: CCO0017 | J73: BOONCHOT BORIWUT | K73: ER | L73: 46077 | M73: 46077 | N73: 46077 | O73: บริษัท สุพรรณ เทเลคอม จำกัด | P73: VD00327 | Q73: SUBCON | R73: Adisak Chanmao | S73: Sermsiri Bampentam | T73: 26WK9 | U73: 0 | V73: 1970 | W73: 0 | X73: 111 | Y73: 2081 | Z73: 0 | AA73: - | AB73: 2081 | AC73: 1500 | AD73: 1301.1 | AE73: 1301.1 | AF73: 0 | AG73: 0 | AH73: Y | AI73: Y | AJ73: Y | AK73: 0 | AL73: 2081 | AM73: 1687 | AN73: 0 | AO73: 1687 | AP73: 1301.1 | AQ73: 1301.1 | AR73: 1687 | AS73: 1301.1 | AT73: 0 | AU73: 46077 | AV73: 46086 | AW73: - | AX73: 394 | AY73: 0 | AZ73: HUAWEI | BD73: 0 | BE73: 9 | BF73: COMPLETED | BG73: IPRAN | BH73: 1687 | BI73: 46087 | BJ73: 10 | BK73: 0 | BN73: 1687 | BO73: 394 | BP73: =G73&BG73 -> TMEIPRAN
A74: EP26020084 | B74: TME-DIS_ATN-CCO0011 | C74: CCO0011-AC-01_D_Dismantle_EAST_R3 | D74: 1687.29 | E74: 2081 | F74: 46066 | G74: TME | H74: DIS_ATN | I74: CCO0011 | J74: BOONCHOT BORIWUT | K74: ER | L74: 46077 | M74: 46077 | N74: 46077 | O74: บริษัท สุพรรณ เทเลคอม จำกัด | P74: VD00327 | Q74: SUBCON | R74: Adisak Chanmao | S74: Sermsiri Bampentam | T74: 26WK9 | U74: 0 | V74: 1970 | W74: 0 | X74: 111 | Y74: 2081 | Z74: 0 | AA74: - | AB74: 2081 | AC74: 1500 | AD74: 1301.1 | AE74: 1301.1 | AF74: 0 | AG74: 0 | AH74: Y | AI74: Y | AJ74: Y | AK74: 0 | AL74: 2081 | AM74: 1687 | AN74: 0 | AO74: 1687 | AP74: 0 | AQ74: 1301.1 | AR74: 1687 | AS74: 1301.1 | AT74: 0 | AU74: 46077 | AV74: 46090 | AW74: - | AX74: 394 | AY74: 0 | AZ74: HUAWEI | BD74: 0 | BE74: 13 | BF74: COMPLETED | BG74: IPRAN | BH74: 1687 | BI74: 46096 | BJ74: 19 | BK74: 0 | BN74: 1687 | BO74: 394 | BP74: =G74&BG74 -> TMEIPRAN
A75: EP26020085 | B75: TME-DIS_ATN-CCS0263 | C75: CCS0263-AC-01_D_Dismantle_EAST_R3 | D75: 1687.29 | E75: 2081 | F75: 46066 | G75: TME | H75: DIS_ATN | I75: CCS0263 | J75: BOONCHOT BORIWUT | K75: ER | L75: 46077 | M75: 46077 | N75: 46077 | O75: บริษัท สุพรรณ เทเลคอม จำกัด | P75: VD00327 | Q75: SUBCON | R75: Adisak Chanmao | S75: Sermsiri Bampentam | T75: 26WK9 | U75: 0 | V75: 1970 | W75: 0 | X75: 111 | Y75: 2081 | Z75: 0 | AA75: - | AB75: 2081 | AC75: 1500 | AD75: 1301.1 | AE75: 1301.1 | AF75: 0 | AG75: 0 | AH75: Y | AI75: Y | AJ75: Y | AK75: 0 | AL75: 2081 | AM75: 1687 | AN75: 0 | AO75: 1687 | AP75: 0 | AQ75: 1301.1 | AR75: 1687 | AS75: 1301.1 | AT75: 0 | AU75: 46077 | AV75: 46086 | AW75: - | AX75: 394 | AY75: 0 | AZ75: HUAWEI | BD75: 0 | BE75: 9 | BF75: COMPLETED | BG75: IPRAN | BH75: 1687 | BI75: 46087 | BJ75: 10 | BK75: 0 | BN75: 1687 | BO75: 394 | BP75: =G75&BG75 -> TMEIPRAN
A76: EP26020086 | B76: TME-REPSFP-PCR0068 | C76: PCR0068-AC-01-PCR0125-AC-01_D_Uplink_10G_EAST_R3 | D76: 2932.56 | E76: 3804 | F76: 46066 | G76: TME | H76: REPSFP | I76: PCR0068 | J76: BOONCHOT BORIWUT | K76: ER | L76: 46072 | M76: 46072 | N76: 46072 | O76: นาย ชัชวาล เคราะห์ดี | P76: VD01205 | Q76: SUBCON | R76: Adisak Chanmao | S76: Sermsiri Bampentam | T76: 26WK8 | U76: 0 | V76: 3804 | W76: 0 | X76: 0 | Y76: 3804 | Z76: 0 | AA76: - | AB76: 3804 | AC76: 2400 | AD76: 2400 | AE76: 2400 | AF76: 0 | AG76: 0 | AH76: Y | AI76: Y | AJ76: Y | AK76: 0 | AL76: 3804 | AM76: 3043.2 | AN76: 0 | AO76: 3043.2 | AP76: 2400 | AQ76: 2400 | AR76: 3043.2 | AS76: 2400 | AT76: 0 | AU76: 46072 | AV76: 46077 | AW76: - | AX76: 760.8 | AY76: 0 | AZ76: HUAWEI | BD76: 0 | BE76: 5 | BF76: COMPLETED | BG76: IPRAN | BH76: 3043.2 | BI76: 46087 | BJ76: 15 | BK76: 760.8 | BL76: 46230 | BM76: 158 | BN76: 3804 | BO76: 0 | BP76: =G76&BG76 -> TMEIPRAN
A77: EP26020087 | B77: TME-NCE_Q126-CBR0529 | C77: CBR0529_D_NCE_Swap_EAST_R3 | D77: 3907.59 | E77: 5054.2 | F77: 46066 | G77: TME | H77: NCE_Q126 | I77: CBR0529 | J77: BOONCHOT BORIWUT | K77: ER | L77: 46077 | M77: 46077 | N77: 46077 | O77: บริษัท สุพรรณ เทเลคอม จำกัด | P77: VD00327 | Q77: SUBCON | R77: Adisak Chanmao | S77: Adisak Chanmao | T77: 26WK9 | U77: 0 | V77: 4711.2 | W77: 0 | X77: 343 | Y77: 5054.2 | Z77: 0 | AA77: - | AB77: 5054.2 | AC77: 3200 | AD77: 3199.82 | AE77: 3199.82 | AF77: 0 | AG77: 0 | AH77: Y | AI77: Y | AJ77: Y | AK77: 0 | AL77: 5054.2 | AM77: 4111.96 | AN77: 0 | AO77: 4111.96 | AP77: 3200.2 | AQ77: 3200.2 | AR77: 4111.96 | AS77: 3200.2 | AT77: 0 | AU77: 46078 | AV77: 46079 | AW77: - | AX77: 942.24 | AY77: -0.38 | AZ77: HUAWEI | BD77: 1 | BE77: 2 | BF77: COMPLETED | BG77: IPRAN | BH77: 4111.96 | BI77: 46087 | BJ77: 10 | BK77: 942.24 | BL77: 46230 | BM77: 153 | BN77: 5054.2 | BO77: 0 | BP77: =G77&BG77 -> TMEIPRAN
A78: EP26030001 | B78: TME-REPSFP-CBI0149 | C78: CBI0149-AC-02-CBR0149-AC-01_D_Flash_Uplink_10G_EAST_R3 | D78: 2932.56 | E78: 3804 | F78: 46095 | G78: TME | H78: REPSFP | I78: CBI0149 | J78: BOONCHOT BORIWUT | K78: ER | L78: 46079 | M78: 46079 | N78: 46079 | O78: นาย ชัชวาล เคราะห์ดี | P78: VD01205 | Q78: SUBCON | R78: Adisak Chanmao | S78: Sermsiri Bampentam | T78: 26WK9 | U78: 0 | V78: 3804 | W78: 0 | X78: 0 | Y78: 3804 | Z78: 0 | AA78: - | AB78: 3804 | AC78: 2400 | AD78: 2400 | AE78: 2400 | AF78: 0 | AG78: 0 | AH78: Y | AI78: Y | AJ78: Y | AK78: 0 | AL78: 3804 | AM78: 3043.2 | AN78: 0 | AO78: 3043.2 | AP78: 2400 | AQ78: 2400 | AR78: 3043.2 | AS78: 2400 | AT78: 0 | AU78: 46079 | AV78: 46084 | AW78: - | AX78: 760.8 | AY78: 0 | AZ78: HUAWEI | BD78: 0 | BE78: 5 | BF78: COMPLETED | BG78: IPRAN | BH78: 3043.2 | BI78: 46087 | BJ78: 8 | BK78: 760.8 | BL78: 46230 | BM78: 151 | BN78: 3804 | BO78: 0 | BP78: =G78&BG78 -> TMEIPRAN
A79: EP26030002 | B79: TME-REPSFP-CBI0184D | C79: CBI0184-AC-01-CBR1428-AC-01_D_Flash_Uplink_10G_EAST_R3 | D79: 2932.56 | E79: 3804 | F79: 46096 | G79: TME | H79: REPSFP | I79: CBI0184D | J79: BOONCHOT BORIWUT | K79: ER | L79: 46078 | M79: 46078 | N79: 46078 | O79: นาย ชัชวาล เคราะห์ดี | P79: VD01205 | Q79: SUBCON | R79: Adisak Chanmao | S79: Sermsiri Bampentam | T79: 26WK9 | U79: 0 | V79: 3804 | W79: 0 | X79: 0 | Y79: 3804 | Z79: 0 | AA79: - | AB79: 3804 | AC79: 2400 | AD79: 2400 | AE79: 2400 | AF79: 0 | AG79: 0 | AH79: Y | AI79: Y | AJ79: Y | AK79: 0 | AL79: 3804 | AM79: 3043.2 | AN79: 0 | AO79: 3043.2 | AP79: 2400 | AQ79: 2400 | AR79: 3043.2 | AS79: 2400 | AT79: 0 | AU79: 46078 | AV79: 46084 | AW79: - | AX79: 760.8 | AY79: 0 | AZ79: HUAWEI | BD79: 0 | BE79: 6 | BF79: COMPLETED | BG79: IPRAN | BH79: 3043.2 | BI79: 46087 | BJ79: 9 | BK79: 760.8 | BL79: 46230 | BM79: 152 | BN79: 3804 | BO79: 0 | BP79: =G79&BG79 -> TMEIPRAN
A80: EP26030003 | B80: TME-REPSFP-CBI0639 | C80: CBI0639-AC-01-CBR0336-AC-01_D_Flash_Uplink_10G_EAST_R3 | D80: 2932.56 | E80: 3804 | F80: 46097 | G80: TME | H80: REPSFP | I80: CBI0639 | J80: BOONCHOT BORIWUT | K80: ER | L80: 46078 | M80: 46078 | N80: 46078 | O80: นาย ชัชวาล เคราะห์ดี | P80: VD01205 | Q80: SUBCON | R80: Adisak Chanmao | S80: Sermsiri Bampentam | T80: 26WK9 | U80: 0 | V80: 3804 | W80: 0 | X80: 0 | Y80: 3804 | Z80: 0 | AA80: - | AB80: 3804 | AC80: 2400 | AD80: 2400 | AE80: 2400 | AF80: 0 | AG80: 0 | AH80: Y | AI80: Y | AJ80: Y | AK80: 0 | AL80: 3804 | AM80: 3043.2 | AN80: 0 | AO80: 3043.2 | AP80: 2400 | AQ80: 2400 | AR80: 3043.2 | AS80: 2400 | AT80: 0 | AU80: 46078 | AV80: 46084 | AW80: - | AX80: 760.8 | AY80: 0 | AZ80: HUAWEI | BD80: 0 | BE80: 6 | BF80: COMPLETED | BG80: IPRAN | BH80: 3043.2 | BI80: 46087 | BJ80: 9 | BK80: 760.8 | BL80: 46230 | BM80: 152 | BN80: 3804 | BO80: 0 | BP80: =G80&BG80 -> TMEIPRAN
A81: EP26030004 | B81: TME-REPSFP-CBR0148 | C81: CBR0148-AC-01-CBI0016-AG-01_D_Flash_Uplink_10G_EAST_R3 | D81: 2932.56 | E81: 3804 | F81: 46098 | G81: TME | H81: REPSFP | I81: CBR0148 | J81: BOONCHOT BORIWUT | K81: ER | L81: 46083 | M81: 46083 | N81: 46083 | O81: นาย ชัชวาล เคราะห์ดี | P81: VD01205 | Q81: SUBCON | R81: Adisak Chanmao | S81: Sermsiri Bampentam | T81: 26WK10 | U81: 0 | V81: 3804 | W81: 0 | X81: 0 | Y81: 3804 | Z81: 0 | AA81: - | AB81: 3804 | AC81: 2400 | AD81: 2400 | AE81: 2400 | AF81: 0 | AG81: 0 | AH81: Y | AI81: Y | AJ81: Y | AK81: 0 | AL81: 3804 | AM81: 3043.2 | AN81: 0 | AO81: 3043.2 | AP81: 2400 | AQ81: 2400 | AR81: 3043.2 | AS81: 2400 | AT81: 0 | AU81: 46079 | AV81: 46085 | AW81: - | AX81: 760.8 | AY81: 0 | AZ81: HUAWEI | BD81: 0 | BE81: 2 | BF81: COMPLETED | BG81: IPRAN | BH81: 3043.2 | BI81: 46101 | BJ81: 18 | BK81: 760.8 | BL81: 46230 | BM81: 147 | BN81: 3804 | BO81: 0 | BP81: =G81&BG81 -> TMEIPRAN
A82: EP26030005 | B82: TME-REPSFP-CBR0192 | C82: CBR0192-AC-01-CBR0148-AC-01_D_Flash_Uplink_10G_EAST_R3 | D82: 2932.56 | E82: 3804 | F82: 46099 | G82: TME | H82: REPSFP | I82: CBR0192 | J82: BOONCHOT BORIWUT | K82: ER | L82: 46079 | M82: 46079 | N82: 46079 | O82: นาย ชัชวาล เคราะห์ดี | P82: VD01205 | Q82: SUBCON | R82: Adisak Chanmao | S82: Sermsiri Bampentam | T82: 26WK9 | U82: 0 | V82: 3804 | W82: 0 | X82: 0 | Y82: 3804 | Z82: 0 | AA82: - | AB82: 3804 | AC82: 2400 | AD82: 2400 | AE82: 2400 | AF82: 0 | AG82: 0 | AH82: Y | AI82: Y | AJ82: Y | AK82: 0 | AL82: 3804 | AM82: 3043.2 | AN82: 0 | AO82: 3043.2 | AP82: 2400 | AQ82: 2400 | AR82: 3043.2 | AS82: 2400 | AT82: 0 | AU82: 46079 | AV82: 46084 | AW82: - | AX82: 760.8 | AY82: 0 | AZ82: HUAWEI | BD82: 0 | BE82: 5 | BF82: COMPLETED | BG82: IPRAN | BH82: 3043.2 | BI82: 46087 | BJ82: 8 | BK82: 760.8 | BL82: 46230 | BM82: 151 | BN82: 3804 | BO82: 0 | BP82: =G82&BG82 -> TMEIPRAN
A83: EP26030006 | B83: TME-REPSFP-CBR0379 | C83: CBR0379-AC-01-CBR1047-AC-01_D_Flash_Uplink_10G_EAST_R3 | D83: 2932.56 | E83: 3804 | F83: 46100 | G83: TME | H83: REPSFP | I83: CBR0379 | J83: BOONCHOT BORIWUT | K83: ER | L83: 46079 | M83: 46079 | N83: 46079 | O83: นาย ชัชวาล เคราะห์ดี | P83: VD01205 | Q83: SUBCON | R83: Adisak Chanmao | S83: Sermsiri Bampentam | T83: 26WK9 | U83: 0 | V83: 3804 | W83: 0 | X83: 0 | Y83: 3804 | Z83: 0 | AA83: - | AB83: 3804 | AC83: 2400 | AD83: 2400 | AE83: 2400 | AF83: 0 | AG83: 0 | AH83: Y | AI83: Y | AJ83: Y | AK83: 0 | AL83: 3804 | AM83: 3043.2 | AN83: 0 | AO83: 3043.2 | AP83: 2400 | AQ83: 2400 | AR83: 3043.2 | AS83: 2400 | AT83: 0 | AU83: 46079 | AV83: 46085 | AW83: - | AX83: 760.8 | AY83: 0 | AZ83: HUAWEI | BD83: 0 | BE83: 6 | BF83: COMPLETED | BG83: IPRAN | BH83: 3043.2 | BI83: 46087 | BJ83: 8 | BK83: 760.8 | BL83: 46230 | BM83: 151 | BN83: 3804 | BO83: 0 | BP83: =G83&BG83 -> TMEIPRAN
A84: EP26030007 | B84: TME-REPSFP-CBR0819 | C84: CBR0819-AC-01-CBR0789-AC-01_D_Flash_Uplink_10G_EAST_R3 | D84: 2932.56 | E84: 3804 | F84: 46101 | G84: TME | H84: REPSFP | I84: CBR0819 | J84: BOONCHOT BORIWUT | K84: ER | L84: 46078 | M84: 46078 | N84: 46078 | O84: นาย ชัชวาล เคราะห์ดี | P84: VD01205 | Q84: SUBCON | R84: Adisak Chanmao | S84: Sermsiri Bampentam | T84: 26WK9 | U84: 0 | V84: 3804 | W84: 0 | X84: 0 | Y84: 3804 | Z84: 0 | AA84: - | AB84: 3804 | AC84: 2400 | AD84: 2400 | AE84: 2400 | AF84: 0 | AG84: 0 | AH84: Y | AI84: Y | AJ84: Y | AK84: 0 | AL84: 3804 | AM84: 3043.2 | AN84: 0 | AO84: 3043.2 | AP84: 2400 | AQ84: 2400 | AR84: 3043.2 | AS84: 2400 | AT84: 0 | AU84: 46078 | AV84: 46084 | AW84: - | AX84: 760.8 | AY84: 0 | AZ84: HUAWEI | BD84: 0 | BE84: 6 | BF84: COMPLETED | BG84: IPRAN | BH84: 3043.2 | BI84: 46087 | BJ84: 9 | BK84: 760.8 | BL84: 46230 | BM84: 152 | BN84: 3804 | BO84: 0 | BP84: =G84&BG84 -> TMEIPRAN
A85: EP26030008 | B85: TME-REPSFP-CBR0898 | C85: CBR0898-AC-01-CBR1017-AC-01_D_Flash_Uplink_10G_EAST_R3 | D85: 2932.56 | E85: 3804 | F85: 46102 | G85: TME | H85: REPSFP | I85: CBR0898 | J85: BOONCHOT BORIWUT | K85: ER | L85: 46078 | M85: 46078 | N85: 46078 | O85: นาย ชัชวาล เคราะห์ดี | P85: VD01205 | Q85: SUBCON | R85: Adisak Chanmao | S85: Sermsiri Bampentam | T85: 26WK9 | U85: 0 | V85: 3804 | W85: 0 | X85: 0 | Y85: 3804 | Z85: 0 | AA85: - | AB85: 3804 | AC85: 2400 | AD85: 2400 | AE85: 2400 | AF85: 0 | AG85: 0 | AH85: Y | AI85: Y | AJ85: Y | AK85: 0 | AL85: 3804 | AM85: 3043.2 | AN85: 0 | AO85: 3043.2 | AP85: 2400 | AQ85: 2400 | AR85: 3043.2 | AS85: 2400 | AT85: 0 | AU85: 46078 | AV85: 46084 | AW85: - | AX85: 760.8 | AY85: 0 | AZ85: HUAWEI | BD85: 0 | BE85: 6 | BF85: COMPLETED | BG85: IPRAN | BH85: 3043.2 | BI85: 46087 | BJ85: 9 | BK85: 760.8 | BL85: 46230 | BM85: 152 | BN85: 3804 | BO85: 0 | BP85: =G85&BG85 -> TMEIPRAN
A86: EP26030010 | B86: TME-REPSFP-CBR1406 | C86: CBR1406-AC-01-CBRC056-AC-01_D_Flash_Uplink_10G_EAST_R3 | D86: 2932.56 | E86: 3804 | F86: 46104 | G86: TME | H86: REPSFP | I86: CBR1406 | J86: BOONCHOT BORIWUT | K86: ER | L86: 46079 | M86: 46079 | N86: 46079 | O86: นาย ชัชวาล เคราะห์ดี | P86: VD01205 | Q86: SUBCON | R86: Adisak Chanmao | S86: Sermsiri Bampentam | T86: 26WK9 | U86: 0 | V86: 3804 | W86: 0 | X86: 0 | Y86: 3804 | Z86: 0 | AA86: - | AB86: 3804 | AC86: 2400 | AD86: 2400 | AE86: 2400 | AF86: 0 | AG86: 0 | AH86: Y | AI86: Y | AJ86: Y | AK86: 0 | AL86: 3804 | AM86: 3043.2 | AN86: 0 | AO86: 3043.2 | AP86: 2400 | AQ86: 2400 | AR86: 3043.2 | AS86: 2400 | AT86: 0 | AU86: 46079 | AV86: 46085 | AW86: - | AX86: 760.8 | AY86: 0 | AZ86: HUAWEI | BD86: 0 | BE86: 6 | BF86: COMPLETED | BG86: IPRAN | BH86: 3043.2 | BI86: 46087 | BJ86: 8 | BK86: 760.8 | BL86: 46230 | BM86: 151 | BN86: 3804 | BO86: 0 | BP86: =G86&BG86 -> TMEIPRAN
A87: EP26030011 | B87: TME-REPSFP-CBR1428 | C87: CBR1428-AC-01-CBR1274-AC-01_D_Flash_Uplink_10G_EAST_R3 | D87: 2932.56 | E87: 3804 | F87: 46105 | G87: TME | H87: REPSFP | I87: CBR1428 | J87: BOONCHOT BORIWUT | K87: ER | L87: 46078 | M87: 46078 | N87: 46078 | O87: นาย ชัชวาล เคราะห์ดี | P87: VD01205 | Q87: SUBCON | R87: Adisak Chanmao | S87: Sermsiri Bampentam | T87: 26WK9 | U87: 0 | V87: 3804 | W87: 0 | X87: 0 | Y87: 3804 | Z87: 0 | AA87: - | AB87: 3804 | AC87: 2400 | AD87: 2400 | AE87: 2400 | AF87: 0 | AG87: 0 | AH87: Y | AI87: Y | AJ87: Y | AK87: 0 | AL87: 3804 | AM87: 3043.2 | AN87: 0 | AO87: 3043.2 | AP87: 2400 | AQ87: 2400 | AR87: 3043.2 | AS87: 2400 | AT87: 0 | AU87: 46078 | AV87: 46084 | AW87: - | AX87: 760.8 | AY87: 0 | AZ87: HUAWEI | BD87: 0 | BE87: 6 | BF87: COMPLETED | BG87: IPRAN | BH87: 3043.2 | BI87: 46087 | BJ87: 9 | BK87: 760.8 | BL87: 46230 | BM87: 152 | BN87: 3804 | BO87: 0 | BP87: =G87&BG87 -> TMEIPRAN
... A90: EP26030014 | B90: TME-REPSFP-CBI0058 | C90: CBI0058-AC-02-CBR0058-AC-01_D_Flash_Uplink_10G_EAST_R3 | D90: 2932.56 | E90: 3804 | F90: 46110 | G90: TME | H90: REPSFP | I90: CBI0058 | J90: BOONCHOT BORIWUT | K90: ER | L90: 46078 | M90: 46078 | N90: 46078 | O90: นาย ชัชวาล เคราะห์ดี | P90: VD01205 | Q90: SUBCON | R90: Adisak Chanmao | S90: Sermsiri Bampentam | T90: 26WK9 | U90: 0 | V90: 3804 | W90: 0 | X90: 0 | Y90: 3804 | Z90: 0 | AA90: - | AB90: 3804 | AC90: 2400 | AD90: 2400 | AE90: 2400 | AF90: 0 | AG90: 0 | AH90: Y | AI90: Y | AJ90: Y | AK90: 0 | AL90: 3804 | AM90: 3043.2 | AN90: 0 | AO90: 3043.2 | AP90: 2400 | AQ90: 2400 | AR90: 3043.2 | AS90: 2400 | AT90: 0 | AU90: 46079 | AV90: 46084 | AW90: - | AX90: 760.8 | AY90: 0 | AZ90: HUAWEI | BD90: 1 | BE90: 6 | BF90: COMPLETED | BG90: IPRAN | BH90: 3043.2 | BI90: 46087 | BJ90: 9 | BK90: 760.8 | BL90: 46230 | BM90: 152 | BN90: 3804 | BO90: 0 | BP90: =G90&BG90 -> TMEIPRAN
A91: EP26020079 | B91: HAE-Cap_Q126-KKFJM | C91: KKFJM_2025 Capacity Expansion Ph5_EXP_ER_Add | D91: 12583.72 | E91: 15346 | F91: 46066 | G91: HAE | H91: Cap_Q126 | I91: KKFJM | J91: BOONCHOT BORIWUT | K91: ER | L91: - | M91: - | O91: INHOUSE PHET SAITHONG | P91: - | Q91: CANCEL | R91: CANCEL | S91: CANCEL | U91: 0 | V91: 0 | W91: 0 | X91: 0 | Y91: 0 | Z91: 0 | AA91: - | AB91: 0 | AC91: 9514.52 | AD91: 0 | AE91: 0 | AF91: 0 | AG91: 0 | AH91: - | AI91: - | AJ91: - | AK91: 793 | AL91: 0 | AM91: 0 | AN91: 0 | AO91: 0 | AP91: 0 | AQ91: 0 | AR91: 0 | AS91: 0 | AT91: 0 | AU91: - | AV91: - | AW91: - | AX91: 0 | AY91: 0 | AZ91: - | BF91: CANCEL | BG91: CANCEL | BH91: 793 | BK91: 0 | BN91: 793 | BO91: 0 | BP91: =G91&BG91 -> HAECANCEL
A92: EP26030015 | B92: TME-AGG_Exp-RYG0004 | C92: RYG0004_D_AGG_Exp_EAST_R3 | D92: 3417.82 | E92: 4413 | F92: 46111 | G92: TME | H92: AGG_Exp | I92: RYG0004 | J92: BOONCHOT BORIWUT | K92: ER | L92: 46087 | M92: 46087 | N92: 46087 | O92: นาย ชัชวาล เคราะห์ดี | P92: VD01205 | Q92: SUBCON | R92: Adisak Chanmao | S92: Adisak Chanmao | T92: 26WK10 | U92: 0 | V92: 4413 | W92: 0 | X92: 0 | Y92: 4413 | Z92: 0 | AA92: - | AB92: 4413 | AC92: 2800 | AD92: 2800 | AE92: 2800 | AF92: 0 | AG92: 0 | AH92: Y | AI92: Y | AJ92: Y | AK92: 0 | AL92: 4413 | AM92: 3530.4 | AN92: 0 | AO92: 3530.4 | AP92: 2800 | AQ92: 2800 | AR92: 3530.4 | AS92: 2240 | AT92: 0 | AU92: 46087 | AV92: 46090 | AW92: - | AX92: 882.6 | AY92: 560 | AZ92: HUAWEI | BD92: 0 | BE92: 3 | BF92: COMPLETED | BG92: IPRAN | BH92: 3530.4 | BI92: 46115 | BJ92: 28 | BK92: 882.6 | BL92: 46230 | BM92: 143 | BN92: 4413 | BO92: 0 | BP92: =G92&BG92 -> TMEIPRAN
A93: EP26030078 | B93: TME-REPSFP-CBI0043D | C93: CBI0043-AG-01_CBI1307-AC-01_D_Rehoming_Bidi_EAS_R3 | D93: 2932.56 | E93: 3804 | F93: 46111 | G93: TME | H93: REPSFP | I93: CBI0043D | J93: BOONCHOT BORIWUT | K93: ER | L93: 46094 | M93: 46094 | N93: 46094 | O93: นาย ชัชวาล เคราะห์ดี | P93: VD01205 | Q93: SUBCON | R93: Adisak Chanmao | S93: Adisak Chanmao | T93: 26WK11 | U93: 0 | V93: 3804 | W93: 0 | X93: 0 | Y93: 3804 | Z93: 0 | AA93: - | AB93: 3804 | AC93: 2400 | AD93: 2400 | AE93: 2400 | AF93: 0 | AG93: 0 | AH93: Y | AI93: Y | AJ93: Y | AK93: 0 | AL93: 3804 | AM93: 3043.2 | AN93: 0 | AO93: 3043.2 | AP93: 2400 | AQ93: 2400 | AR93: 3043.2 | AS93: 1920 | AT93: 0 | AU93: 46094 | AV93: 46115 | AW93: - | AX93: 760.8 | AY93: 480 | AZ93: HUAWEI | BD93: 0 | BE93: 21 | BF93: COMPLETED | BG93: IPRAN | BH93: 3043.2 | BI93: 46115 | BJ93: 21 | BK93: 760.8 | BL93: 46230 | BM93: 136 | BN93: 3804 | BO93: 0 | BP93: =G93&BG93 -> TMEIPRAN
A94: EP26030079 | B94: TME-REPSFP-PCR0012 | C94: PCR0012-AC-01-PRI0050-AC-02_D_Flash_Uplink_10G_EAST_R3 | D94: 2932.56 | E94: 3804 | F94: 46111 | G94: TME | H94: REPSFP | I94: PCR0012 | J94: BOONCHOT BORIWUT | K94: ER | L94: 46093 | M94: 46093 | N94: 46093 | O94: นาย ชัชวาล เคราะห์ดี | P94: VD01205 | Q94: SUBCON | R94: Adisak Chanmao | S94: Adisak Chanmao | T94: 26WK11 | U94: 0 | V94: 3804 | W94: 0 | X94: 0 | Y94: 3804 | Z94: 0 | AA94: - | AB94: 3804 | AC94: 2400 | AD94: 2400 | AE94: 2400 | AF94: 0 | AG94: 0 | AH94: Y | AI94: Y | AJ94: Y | AK94: 0 | AL94: 3804 | AM94: 3043.2 | AN94: 0 | AO94: 3043.2 | AP94: 2400 | AQ94: 2400 | AR94: 3043.2 | AS94: 2400 | AT94: 0 | AU94: 46093 | AV94: 46097 | AW94: - | AX94: 760.8 | AY94: 0 | AZ94: HUAWEI | BD94: 0 | BE94: 4 | BF94: COMPLETED | BG94: IPRAN | BH94: 3043.2 | BI94: 46115 | BJ94: 22 | BK94: 760.8 | BL94: 46230 | BM94: 137 | BN94: 3804 | BO94: 0 | BP94: =G94&BG94 -> TMEIPRAN
A95: EP26030080 | B95: TME-REPSFP-PRI0131 | C95: PRI0131-AC-01-PCR0138-AC-01_D_Flash_Uplink_10G_EAST_R3 | D95: 2932.56 | E95: 3804 | F95: 46111 | G95: TME | H95: REPSFP | I95: PRI0131 | J95: BOONCHOT BORIWUT | K95: ER | L95: 46093 | M95: 46093 | N95: 46093 | O95: นาย ชัชวาล เคราะห์ดี | P95: VD01205 | Q95: SUBCON | R95: Adisak Chanmao | S95: Adisak Chanmao | T95: 26WK11 | U95: 0 | V95: 3804 | W95: 0 | X95: 0 | Y95: 3804 | Z95: 0 | AA95: - | AB95: 3804 | AC95: 2400 | AD95: 2400 | AE95: 2400 | AF95: 0 | AG95: 0 | AH95: Y | AI95: Y | AJ95: Y | AK95: 0 | AL95: 3804 | AM95: 3043.2 | AN95: 0 | AO95: 3043.2 | AP95: 2400 | AQ95: 2400 | AR95: 3043.2 | AS95: 2400 | AT95: 0 | AU95: 46093 | AV95: 46097 | AW95: - | AX95: 760.8 | AY95: 0 | AZ95: HUAWEI | BD95: 0 | BE95: 4 | BF95: COMPLETED | BG95: IPRAN | BH95: 3043.2 | BI95: 46115 | BJ95: 22 | BK95: 760.8 | BL95: 46230 | BM95: 137 | BN95: 3804 | BO95: 0 | BP95: =G95&BG95 -> TMEIPRAN
A96: EP26030081 | B96: TME-REPSFP-CBI0587D | C96: CBI0587-AC-01_D_Rehoming_FPT_EAS_R3 | D96: 2050.47 | E96: 2783 | F96: 46111 | G96: TME | H96: REPSFP | I96: CBI0587D | J96: BOONCHOT BORIWUT | K96: ER | L96: 46094 | M96: 46094 | N96: 46094 | O96: นาย ชัชวาล เคราะห์ดี | P96: VD01205 | Q96: SUBCON | R96: Adisak Chanmao | S96: Adisak Chanmao | T96: 26WK11 | U96: 0 | V96: 1413 | W96: 1370 | X96: 0 | Y96: 2783 | Z96: 0 | AA96: - | AB96: 2783 | AC96: 1800 | AD96: 1630 | AE96: 1630 | AF96: 0 | AG96: 0 | AH96: Y | AI96: Y | AJ96: Y | AK96: 0 | AL96: 2783 | AM96: 2500.4 | AN96: 0 | AO96: 2500.4 | AP96: 1630 | AQ96: 1630 | AR96: 2500.4 | AS96: 1304 | AT96: 0 | AU96: 46094 | AV96: 46118 | AW96: - | AX96: 282.6 | AY96: 326 | AZ96: HUAWEI | BD96: 0 | BE96: 24 | BF96: COMPLETED | BG96: IPRAN | BH96: 2500.4 | BI96: 46115 | BJ96: 21 | BK96: 0 | BN96: 2500.4 | BO96: 282.6 | BP96: =G96&BG96 -> TMEIPRAN
A97: EP26030083 | B97: TME-REPSFP-CBR0886 | C97: CBR0886-AC-01-CBR0300-AC-01_D_Uplink_20G_EAST_R3 | D97: 2932.56 | E97: 3804 | F97: 46111 | G97: TME | H97: REPSFP | I97: CBR0886 | J97: BOONCHOT BORIWUT | K97: ER | L97: 46097 | M97: 46097 | N97: 46097 | O97: นาย ชัชวาล เคราะห์ดี | P97: VD01205 | Q97: SUBCON | R97: Adisak Chanmao | S97: Adisak Chanmao | T97: 26WK12 | U97: 0 | V97: 3804 | W97: 0 | X97: 0 | Y97: 3804 | Z97: 0 | AA97: - | AB97: 3804 | AC97: 2400 | AD97: 2400 | AE97: 2400 | AF97: 0 | AG97: 0 | AH97: Y | AI97: Y | AJ97: Y | AK97: 0 | AL97: 3804 | AM97: 3043.2 | AN97: 0 | AO97: 3043.2 | AP97: 2400 | AQ97: 2400 | AR97: 3043.2 | AS97: 2400 | AT97: 0 | AU97: 46097 | AV97: 46099 | AW97: - | AX97: 760.8 | AY97: 0 | AZ97: HUAWEI | BD97: 0 | BE97: 2 | BF97: COMPLETED | BG97: IPRAN | BH97: 3043.2 | BI97: 46115 | BJ97: 18 | BK97: 760.8 | BL97: 46230 | BM97: 133 | BN97: 3804 | BO97: 0 | BP97: =G97&BG97 -> TMEIPRAN
A98: EP26030084 | B98: TME-REPSFP-CBI0016 | C98: CBI0016-AG-01-CBR0266-AC-01_D_Uplink_20G_EAST_R3 | D98: 2932.56 | E98: 3804 | F98: 46111 | G98: TME | H98: REPSFP | I98: CBI0016 | J98: BOONCHOT BORIWUT | K98: ER | L98: 46093 | M98: 46093 | N98: 46093 | O98: นาย ชัชวาล เคราะห์ดี | P98: VD01205 | Q98: SUBCON | R98: Adisak Chanmao | S98: Adisak Chanmao | T98: 26WK11 | U98: 0 | V98: 3804 | W98: 0 | X98: 0 | Y98: 3804 | Z98: 0 | AA98: - | AB98: 3804 | AC98: 2400 | AD98: 2400 | AE98: 2400 | AF98: 0 | AG98: 0 | AH98: Y | AI98: Y | AJ98: Y | AK98: 0 | AL98: 3804 | AM98: 3043.2 | AN98: 0 | AO98: 3043.2 | AP98: 2400 | AQ98: 2400 | AR98: 3043.2 | AS98: 2400 | AT98: 0 | AU98: 46094 | AV98: 46097 | AW98: - | AX98: 760.8 | AY98: 0 | AZ98: HUAWEI | BD98: 1 | BE98: 4 | BF98: COMPLETED | BG98: IPRAN | BH98: 3043.2 | BI98: 46115 | BJ98: 22 | BK98: 760.8 | BL98: 46230 | BM98: 137 | BN98: 3804 | BO98: 0 | BP98: =G98&BG98 -> TMEIPRAN
A99: EP26030086 | B99: TME-REPSFP-CBR0266 | C99: CBR0266-AC-01-CBR0886-AC-01_D_Uplink_20G_EAST_R3 | D99: 2932.56 | E99: 3804 | F99: 46111 | G99: TME | H99: REPSFP | I99: CBR0266 | J99: BOONCHOT BORIWUT | K99: ER | L99: 46097 | M99: 46097 | N99: 46097 | O99: นาย ชัชวาล เคราะห์ดี | P99: VD01205 | Q99: SUBCON | R99: Adisak Chanmao | S99: Adisak Chanmao | T99: 26WK12 | U99: 0 | V99: 3804 | W99: 0 | X99: 0 | Y99: 3804 | Z99: 0 | AA99: - | AB99: 3804 | AC99: 2400 | AD99: 2400 | AE99: 2400 | AF99: 0 | AG99: 0 | AH99: Y | AI99: Y | AJ99: Y | AK99: 0 | AL99: 3804 | AM99: 3043.2 | AN99: 0 | AO99: 3043.2 | AP99: 2400 | AQ99: 2400 | AR99: 3043.2 | AS99: 2400 | AT99: 0 | AU99: 46097 | AV99: 46099 | AW99: - | AX99: 760.8 | AY99: 0 | AZ99: HUAWEI | BD99: 0 | BE99: 2 | BF99: COMPLETED | BG99: IPRAN | BH99: 3043.2 | BI99: 46115 | BJ99: 18 | BK99: 760.8 | BL99: 46230 | BM99: 133 | BN99: 3804 | BO99: 0 | BP99: =G99&BG99 -> TMEIPRAN
A100: EP26030088 | B100: TME-DIS_ATN-PRI0005 | C100: PRI0005-AC-01_D_Dismantle_EAST_R3 | D100: 1537.29 | E100: 2081 | F100: 46111 | G100: TME | H100: DIS_ATN | I100: PRI0005 | J100: BOONCHOT BORIWUT | K100: ER | L100: 46093 | M100: 46093 | N100: 46093 | O100: นาย ชัชวาล เคราะห์ดี | P100: VD01205 | Q100: SUBCON | R100: Adisak Chanmao | S100: Adisak Chanmao | T100: 26WK11 | U100: 0 | V100: 1970 | W100: 0 | X100: 111 | Y100: 2081 | Z100: 0 | AA100: - | AB100: 2081 | AC100: 1350 | AD100: 1230 | AE100: 1230 | AF100: 0 | AG100: 0 | AH100: Y | AI100: Y | AJ100: Y | AK100: 0 | AL100: 2081 | AM100: 1687 | AN100: 0 | AO100: 1687 | AP100: 1230 | AQ100: 1230 | AR100: 1687 | AS100: 984 | AT100: 0 | AU100: 46093 | AV100: 46115 | AW100: - | AX100: 394 | AY100: 246 | AZ100: HUAWEI | BD100: 0 | BE100: 22 | BF100: COMPLETED | BG100: IPRAN | BH100: 1687 | BI100: 46115 | BJ100: 22 | BK100: 0 | BN100: 1687 | BO100: 394 | BP100: =G100&BG100 -> TMEIPRAN
A101: EP26030112 | B101: HAE-NEWSITE-CPGCM | C101: CPGCM_2024 Coverage Expansion Ph2_New Site_ER | D101: 21666.04 | E101: 26422 | F101: 46111 | G101: HAE | H101: NEWSITE | I101: CPGCM | J101: BOONCHOT BORIWUT | K101: ER | L101: 46097 | M101: 46100 | N101: 46100 | O101: INHOUSE Adirek Kong-ang | P101: - | Q101: INHOUSE | R101: Adisak Chanmao | S101: Adisak Chanmao | T101: 26WK12 | U101: 793 | V101: 24043 | W101: 0 | X101: 1586 | Y101: 26422 | Z101: 0 | AA101: - | AB101: 26422 | AC101: 16381.64 | AD101: 300 | AE101: 300 | AF101: 300 | AG101: 0 | AH101: Y | AI101: Y | AJ101: Y | AK101: 0 | AL101: 26422 | AM101: 19982.8 | AN101: 6439.2 | AO101: 26422 | AP101: 300 | AQ101: 300 | AR101: 26422 | AS101: 0 | AT101: 5284.4 | AU101: 46105 | AV101: 46106 | AW101: - | AX101: 0 | AY101: 300 | AZ101: HUAWEI | BD101: 5 | BE101: 6 | BF101: COMPLETED | BG101: MBB | BH101: 19982.8 | BI101: 46115 | BJ101: 15 | BK101: 6439.2 | BL101: 46115 | BM101: 15 | BN101: 26422 | BO101: 0 | BP101: =G101&BG101 -> HAEMBB
A102: EP26030082 | B102: TME-DIS_ATN-RYG0777 | C102: RYG0777-AC-01_D_Dismantle_EAST_R3 | D102: 1537.29 | E102: 2081 | F102: 46111 | G102: TME | H102: DIS_ATN | I102: RYG0777 | J102: BOONCHOT BORIWUT | K102: ER | L102: 46099 | M102: 46099 | N102: 46099 | O102: นาย ชัชวาล เคราะห์ดี | P102: VD01205 | Q102: SUBCON | R102: Adisak Chanmao | S102: Adisak Chanmao | T102: 26WK12 | U102: 0 | V102: 1970 | W102: 0 | X102: 111 | Y102: 2081 | Z102: 0 | AA102: - | AB102: 2081 | AC102: 1350 | AD102: 1230 | AE102: 1230 | AF102: 0 | AG102: 0 | AH102: Y | AI102: Y | AJ102: Y | AK102: 0 | AL102: 2081 | AM102: 1687 | AN102: 0 | AO102: 1687 | AP102: 1230 | AQ102: 1230 | AR102: 1687 | AS102: 984 | AT102: 0 | AU102: 46099 | AV102: 46119 | AW102: - | AX102: 394 | AY102: 246 | AZ102: HUAWEI | BD102: 0 | BE102: 20 | BF102: COMPLETED | BG102: IPRAN | BH102: 1687 | BI102: 46115 | BJ102: 16 | BK102: 0 | BN102: 1687 | BO102: 394 | BP102: =G102&BG102 -> TMEIPRAN
...

Sheet Sheet1
B2: WEEK35 | C2: Column Labels | Q2: PMOwner | R2: BOONCHOT BORIWUT
C3: AC1 DONE | F3: FULFILLED | I3: UNFULFILL | L3: Total Count of P+L | M3: Total Sum of REVENUE | N3: Total Sum of REMAIN | Q3: STATUS WORK | R3: CONFIRMED
B4: Row Labels | C4: Count of P+L | D4: Sum of REVENUE | E4: Sum of REMAIN | F4: Count of P+L | G4: Sum of REVENUE | H4: Sum of REMAIN | I4: Count of P+L | J4: Sum of REVENUE | K4: Sum of REMAIN
B5: 2022 | F5: 3588 | G5: 8008048.9 | H5: 0 | L5: 3588 | M5: 8008048.9 | N5: 0 | Q5: Sum of REMAIN | R5: Column Labels
B6: 2023 | C6: 3 | D6: 38065 | E6: 11419.5 | F6: 5228 | G6: 11118732 | H6: 43613.1 | I6: 11 | J6: 78217 | K6: 78217 | L6: 5242 | M6: 11235014 | N6: 133249.6 | Q6: Row Labels | R6: HUAWEI | S6: Grand Total
B7: 2024 | F7: 5178 | G7: 14508273 | H7: 12891.9 | I7: 12 | J7: 60400 | K7: 60400 | L7: 5190 | M7: 14568673 | N7: 73291.9 | Q7: INSTALL ONPROCESS | R7: 820474 | S7: 820474
B8: 2025 | C8: 10 | D8: 31786 | E8: 9535.8 | F8: 3004 | G8: 8392750.2 | H8: 43148.1 | I8: 2 | J8: 24488 | K8: 24488 | L8: 3016 | M8: 8449024.2 | N8: 77171.9 | Q8: 2026 | R8: 820474 | S8: 820474
B9: 2026 | C9: 220 | D9: 676569 | E9: 203100.74 | F9: 1561 | G9: 3601009.4 | H9: 107470.92 | I9: 326 | J9: 935261 | K9: 935261 | L9: 2107 | M9: 5212839.4 | N9: 1245832.7 | Q9: Acceptance Plan AUGUST | R9: 324780.72 | S9: 324780.72
B10: Grand Total | C10: 233 | D10: 746420 | E10: 224056.04 | F10: 18559 | G10: 45628814 | H10: 207124.02 | I10: 351 | J10: 1098366 | K10: 1098366 | L10: 19143 | M10: 47473600 | N10: 1529546.1 | Q10: 2023 | R10: 87202.9 | S10: 87202.9
Q11: 2024 | R11: 62257 | S11: 62257
B12: WEEK36 | C12: Column Labels | Q12: 2025 | R12: 67636.1 | S12: 67636.1
C13: AC1 DONE | F13: FULFILLED | I13: UNFULFILL | L13: Total Count of P+L | M13: Total Sum of REVENUE | N13: Total Sum of REMAIN | Q13: 2026 | R13: 107684.72 | S13: 107684.72
B14: Row Labels | C14: Count of P+L | D14: Sum of REVENUE | E14: Sum of REMAIN | F14: Count of P+L | G14: Sum of REVENUE | H14: Sum of REMAIN | I14: Count of P+L | J14: Sum of REVENUE | K14: Sum of REMAIN | Q14: Acctance DONE AUGUST | R14: 29088 | S14: 29088
B15: 2022 | F15: 3588 | G15: 8008048.9 | H15: 0 | L15: 3588 | M15: 8008048.9 | N15: 0 | Q15: 2025 | R15: 29088 | S15: 29088
B16: 2023 | C16: 9 | D16: 118924 | E16: 25739.04 | F16: 5220 | G16: 11003308 | H16: 8985.9 | I16: 13 | J16: 112782 | K16: 112782 | L16: 5242 | M16: 11235014 | N16: 147506.94 | Q16: 2026 | R16: 0 | S16: 0
B17: 2024 | C17: 8 | D17: 36783 | E17: 7724.43 | F17: 5170 | G17: 14471490 | H17: 1857 | I17: 12 | J17: 60400 | K17: 60400 | L17: 5190 | M17: 14568673 | N17: 69981.43 | Q17: Acctance Plan AC#2 WK36 | R17: 110759.4 | S17: 110759.4
B18: 2025 | C18: 3 | D18: 69000 | E18: 27600 | F18: 2999 | G18: 8320147.2 | H18: 43148.1 | I18: 13 | J18: 57762 | K18: 57762 | L18: 3015 | M18: 8446909.2 | N18: 128510.1 | Q18: 2026 | R18: 110759.4 | S18: 110759.4
B19: 2026 | C19: 154 | D19: 472544 | E19: 142200.5 | F19: 1706 | G19: 4017920.4 | H19: 106536.12 | I19: 260 | J19: 768097 | K19: 768097 | L19: 2120 | M19: 5258561.4 | N19: 1016833.6 | Q19: Acctance Plan AC#1 WK36 | R19: 182483 | S19: 182483
B20: Grand Total | C20: 174 | D20: 697251 | E20: 203263.97 | F20: 18683 | G20: 45820915 | H20: 160527.12 | I20: 298 | J20: 999041 | K20: 999041 | L20: 19155 | M20: 47517207 | N20: 1362832.1 | Q20: 2026 | R20: 182483 | S20: 182483
Q21: Grand Total | R21: 1467585.1 | S21: 1467585.1
P27: AC1 | Q27: 2023
P28: AC1 | Q28: 2024
P29: AC1 | Q29: 2025
P30: AC1 | Q30: 2026 | R30: 182483
P32: AC2 | Q32: 2023
P33: AC2 | Q33: 2024
P34: AC2 | Q34: 2025 | R34: 29088
P35: AC2 | Q35: 2026 | R35: 110759.4
